Workbook

Sheet Cover
A1: Equity Research Teardown — Broadcom Inc. (NASDAQ: AVGO)
A2: Independent equity research project by Archit Chawla | As of October 19, 2026
A4: Current price (Oct 16, 2026 close) | B4: 328.75
A5: Recommendation | B5: PASS
A6: One-line thesis | B6: AI networking plus a software cash machine — but the quote prices the VMware flywheel as fully derisked; my bull case is only fair value at today's rate regime.
A8: Contents
A9: Assumptions | B9: WACC build and all forecast drivers; [DATA] vs [JUDGMENT] tags
A10: Historicals | B10: Financials from Yahoo Finance annual statements (FY2022–FY2025 (fiscal year ends October))
A11: DCF_Base / DCF_Bull / DCF_Bear | B11: 5-year DCF per case; all formulas live
A12: Comps | B12: NVDA, AMD, ALAB: EV/Revenue, EV/EBITDA, P/E and implied ranges
A13: Checks | B13: Verification appendix: tie-outs and data sources
A14: Sources | B14: Full URLs and access dates
A16: Disclaimer: Independent project for skill demonstration; not investment advice.

Sheet Assumptions
A1: Assumptions
A2: Blue cells are inputs. [DATA] = market/filing data; [JUDGMENT] = analyst estimate with rationale.
A3: WACC build
A4: Risk-free rate (US 10Y) | B4: 0.051 | C4: [DATA] | D4: 5.09% on 2026-10-19 (Reuters); rounded to 5.1%
A5: Equity risk premium | B5: 0.045 | C5: [JUDGMENT] | D5: Long-run US ERP assumption
A6: Beta (AVGO) | B6: 1.48 | C6: [DATA] | D6: Yahoo Finance 1.476 (2026-10-19); cross-checked MarketBeat 1.46, Finnhub 1.49
A7: Cost of equity (CAPM) | B7: =Assumptions!$B$4+Assumptions!$B$6*Assumptions!$B$5 | C7: [CALC] | D7: Rf + beta × ERP
A8: Pre-tax cost of debt | B8: 0.06 | C8: [JUDGMENT] | D8: BBB-grade, leveraged balance sheet; through-cycle new-issue estimate
A9: Marginal tax rate | B9: 0.21 | C9: [JUDGMENT] | D9: US statutory; FY2025 provision was a –$397M benefit (valuation allowance) — normalized
A10: After-tax cost of debt | B10: =Assumptions!$B$8*(1-Assumptions!$B$9) | C10: [CALC]
A11: Market value of equity ($M) | B11: 1620074.6 | C11: [DATA] | D11: Yahoo Finance 2026-10-19 ($1.62T); price × shares cross-check: $1.57T
A12: Book value of debt ($M) | B12: 59419 | C12: [DATA] | D12: Q3 FY2026 balance sheet (2026-07-31)
A13: Weight of equity | B13: =Assumptions!$B$11/(Assumptions!$B$11+Assumptions!$B$12) | C13: [CALC]
A14: Weight of debt | B14: =Assumptions!$B$12/(Assumptions!$B$11+Assumptions!$B$12) | C14: [CALC]
A15: WACC — base case | B15: =Assumptions!$B$13*Assumptions!$B$7+Assumptions!$B$14*Assumptions!$B$10 | C15: [CALC]
A16: WACC — bull case (-100 bps) | B16: =Assumptions!$B$15-0.01 | C16: [CALC] | D16: Rate-normalization scenario
A17: WACC — bear case (+100 bps) | B17: =Assumptions!$B$15+0.01 | C17: [CALC] | D17: Higher-for-longer scenario
A19: Forecast drivers (FY2026–FY2030)
B20: 2026 | C20: 2027 | D20: 2028 | E20: 2029 | F20: 2030
A21: Revenue growth — base | B21: 0.45 | C21: 0.3 | D21: 0.2 | E21: 0.15 | F21: 0.12 | G21: [JUDGMENT] | H21: Q3 FY2026 revenue +85.5% YoY ($29.59B); taper from FY2025 +23.9% (VMware comp annualizes)
A22: Revenue growth — bull | B22: 0.55 | C22: 0.38 | D22: 0.28 | E22: 0.22 | F22: 0.18 | G22: [JUDGMENT] | H22: AI networking (XPU/Ethernet) plus VMware cross-sell sustains 30%+ growth
A23: Revenue growth — bear | B23: 0.35 | C23: 0.18 | D23: 0.05 | E23: -0.12 | F23: 0.08 | G23: [JUDGMENT] | H23: Semi down-cycle in FY2029 (−12%): enterprise IT digestion after the AI build-out
A24: EBITDA margin — base | B24: 0.55 | C24: 0.56 | D24: 0.57 | E24: 0.58 | F24: 0.59 | G24: [JUDGMENT] | H24: FY2025 EBITDA margin 54.3%; expand toward 59% on software/VMware mix
A25: EBITDA margin — bull | B25: 0.57 | C25: 0.59 | D25: 0.6 | E25: 0.61 | F25: 0.62 | G25: [JUDGMENT] | H25: Faster operating leverage as VMware margins fully annualize
A26: EBITDA margin — bear | B26: 0.52 | C26: 0.51 | D26: 0.5 | E26: 0.49 | F26: 0.5 | G26: [JUDGMENT] | H26: Margin pressure from pricing competition and mix shift in the down year
A28: D&A (% of revenue) | B28: 0.12 | G28: [JUDGMENT] | H28: FY2025: 13.7% of revenue (VMware intangibles amortizing); declining
A29: Stock-based comp. (% of revenue) | B29: 0.105 | C29: 0.095 | D29: 0.085 | E29: 0.075 | F29: 0.07 | G29: [JUDGMENT] | H29: FY2025: 11.8% of revenue; elevated post-VMware, normalizing
A30: Capex (% of revenue) | B30: 0.01 | G30: [JUDGMENT] | H30: FY2025: 1.0% of revenue (fabless + asset-light software)
A31: Change in NWC (% of revenue growth) | B31: 0.05 | G31: [JUDGMENT] | H31: Receivables/inventory scale with semi activity
A32: Terminal growth — base | B32: 0.03 | G32: [JUDGMENT] | H32: Long-run nominal GDP
A33: Terminal growth — bull | B33: 0.035 | G33: [JUDGMENT]
A34: Terminal growth — bear | B34: 0.02 | G34: [JUDGMENT]
A35: Net debt ($M) | B35: 35444 | G35: [DATA] | H35: Q3 FY2026 (2026-07-31): total debt $59,419M less cash & equivalents $23,975M
A36: Diluted shares outstanding (M) | B36: 4773.6 | G36: [DATA] | H36: Yahoo Finance sharesOutstanding, Oct 2026 (FY2025 diluted weighted avg: 4,853M)

Sheet Historicals
A1: Historical financials — AVGO
A2: $ millions. Source: Yahoo Finance annual statements (filing-derived), as of 2026-10-19. FY2021 column blank in the Yahoo Finance pull — excluded.
B3: 2022 | C3: 2023 | D3: 2024 | E3: 2025
A4: Total revenue | B4: 33203 | C4: 35819 | D4: 51574 | E4: 63887
A5: Gross profit | B5: 22095 | C5: 24690 | D5: 32509 | E5: 43294
A6: EBITDA | B6: 19155 | C6: 20554 | D6: 23879 | E6: 34714
A7: EBITDA margin | B7: =B6/B4 | C7: =C6/C4 | D7: =D6/D4 | E7: =E6/E4
A8: Operating income | B8: 14282 | C8: 16451 | D8: 14996 | E8: 26075
A9: Net income | B9: 11495 | C9: 14082 | D9: 5895 | E9: 23126
A10: Diluted average shares (M) | B10: 4230 | C10: 4270 | D10: 4778 | E10: 4853
A11: Operating cash flow | B11: 16736 | C11: 18085 | D11: 19962 | E11: 27537
A12: Capital expenditures | B12: -424 | C12: -452 | D12: -548 | E12: -623
A13: Free cash flow | B13: 16312 | C13: 17633 | D13: 19414 | E13: 26914
A14: Cash & equivalents | B14: 12416 | C14: 14189 | D14: 9348 | E14: 16178
A15: Total debt | B15: 39515 | C15: 39229 | D15: 67566 | E15: 65136
A16: Revenue growth | C16: =C4/B4-1 | D16: =D4/C4-1 | E16: =E4/D4-1

Sheet DCF_Base
A1: Broadcom Inc. (AVGO) — Discounted cash flow — base case
A2: $ millions, except per-share. All formulas reference Assumptions / Historicals.
B3: 2026 | C3: 2027 | D3: 2028 | E3: 2029 | F3: 2030
A4: Revenue | B4: =Historicals!$E$4*(1+Assumptions!B$21) | C4: =B4*(1+Assumptions!C$21) | D4: =C4*(1+Assumptions!D$21) | E4: =D4*(1+Assumptions!E$21) | F4: =E4*(1+Assumptions!F$21)
A5: Revenue growth | B5: =B4/Historicals!$E$4-1 | C5: =C4/B4-1 | D5: =D4/C4-1 | E5: =E4/D4-1 | F5: =F4/E4-1
A6: EBITDA margin | B6: =Assumptions!B$24 | C6: =Assumptions!C$24 | D6: =Assumptions!D$24 | E6: =Assumptions!E$24 | F6: =Assumptions!F$24
A7: EBITDA | B7: =B4*B6 | C7: =C4*C6 | D7: =D4*D6 | E7: =E4*E6 | F7: =F4*F6
A8: Less: Depreciation & amortization | B8: =B4*Assumptions!$B$28 | C8: =C4*Assumptions!$B$28 | D8: =D4*Assumptions!$B$28 | E8: =E4*Assumptions!$B$28 | F8: =F4*Assumptions!$B$28
A9: EBIT | B9: =B7-B8 | C9: =C7-C8 | D9: =D7-D8 | E9: =E7-E8 | F9: =F7-F8
A10: Tax rate | B10: =Assumptions!$B$9 | C10: =Assumptions!$B$9 | D10: =Assumptions!$B$9 | E10: =Assumptions!$B$9 | F10: =Assumptions!$B$9
A11: Less: Income tax | B11: =B9*B10 | C11: =C9*C10 | D11: =D9*D10 | E11: =E9*E10 | F11: =F9*F10
A12: NOPAT | B12: =B9-B11 | C12: =C9-C11 | D12: =D9-D11 | E12: =E9-E11 | F12: =F9-F11
A13: Add: Stock-based compensation | B13: =B4*Assumptions!B$29 | C13: =C4*Assumptions!C$29 | D13: =D4*Assumptions!D$29 | E13: =E4*Assumptions!E$29 | F13: =F4*Assumptions!F$29
A14: Less: Capital expenditures | B14: =B4*Assumptions!$B$30 | C14: =C4*Assumptions!$B$30 | D14: =D4*Assumptions!$B$30 | E14: =E4*Assumptions!$B$30 | F14: =F4*Assumptions!$B$30
A15: Less: Change in net working capital | B15: =(B4-Historicals!$E$4)*Assumptions!$B$31 | C15: =(C4-B4)*Assumptions!$B$31 | D15: =(D4-C4)*Assumptions!$B$31 | E15: =(E4-D4)*Assumptions!$B$31 | F15: =(F4-E4)*Assumptions!$B$31
A16: Unlevered free cash flow | B16: =B12+B8+B13-B14-B15 | C16: =C12+C8+C13-C14-C15 | D16: =D12+D8+D13-D14-D15 | E16: =E12+E8+E13-E14-E15 | F16: =F12+F8+F13-F14-F15
A17: Discount factor | B17: =1/(1+Assumptions!$B$15)^1 | C17: =1/(1+Assumptions!$B$15)^2 | D17: =1/(1+Assumptions!$B$15)^3 | E17: =1/(1+Assumptions!$B$15)^4 | F17: =1/(1+Assumptions!$B$15)^5
A18: Present value of FCF | B18: =B16*B17 | C18: =C16*C17 | D18: =D16*D17 | E18: =E16*E17 | F18: =F16*F17
A19: Sum of PV of FCF | B19: =SUM(B18:F18)
A20: Terminal value | B20: =F16*(1+Assumptions!$B$32)/(Assumptions!$B$15-Assumptions!$B$32)
A21: PV of terminal value | B21: =B20/(1+Assumptions!$B$15)^5
A22: Enterprise value | B22: =B19+B21
A23: Less: Net debt | B23: =Assumptions!$B$35
A24: Equity value | B24: =B22-B23
A25: Diluted shares outstanding (M) | B25: =Assumptions!$B$36
A26: Implied value per share ($) | B26: =B24/B25

Sheet DCF_Bull
A1: Broadcom Inc. (AVGO) — Discounted cash flow — bull case
A2: $ millions, except per-share. All formulas reference Assumptions / Historicals.
B3: 2026 | C3: 2027 | D3: 2028 | E3: 2029 | F3: 2030
A4: Revenue | B4: =Historicals!$E$4*(1+Assumptions!B$22) | C4: =B4*(1+Assumptions!C$22) | D4: =C4*(1+Assumptions!D$22) | E4: =D4*(1+Assumptions!E$22) | F4: =E4*(1+Assumptions!F$22)
A5: Revenue growth | B5: =B4/Historicals!$E$4-1 | C5: =C4/B4-1 | D5: =D4/C4-1 | E5: =E4/D4-1 | F5: =F4/E4-1
A6: EBITDA margin | B6: =Assumptions!B$25 | C6: =Assumptions!C$25 | D6: =Assumptions!D$25 | E6: =Assumptions!E$25 | F6: =Assumptions!F$25
A7: EBITDA | B7: =B4*B6 | C7: =C4*C6 | D7: =D4*D6 | E7: =E4*E6 | F7: =F4*F6
A8: Less: Depreciation & amortization | B8: =B4*Assumptions!$B$28 | C8: =C4*Assumptions!$B$28 | D8: =D4*Assumptions!$B$28 | E8: =E4*Assumptions!$B$28 | F8: =F4*Assumptions!$B$28
A9: EBIT | B9: =B7-B8 | C9: =C7-C8 | D9: =D7-D8 | E9: =E7-E8 | F9: =F7-F8
A10: Tax rate | B10: =Assumptions!$B$9 | C10: =Assumptions!$B$9 | D10: =Assumptions!$B$9 | E10: =Assumptions!$B$9 | F10: =Assumptions!$B$9
A11: Less: Income tax | B11: =B9*B10 | C11: =C9*C10 | D11: =D9*D10 | E11: =E9*E10 | F11: =F9*F10
A12: NOPAT | B12: =B9-B11 | C12: =C9-C11 | D12: =D9-D11 | E12: =E9-E11 | F12: =F9-F11
A13: Add: Stock-based compensation | B13: =B4*Assumptions!B$29 | C13: =C4*Assumptions!C$29 | D13: =D4*Assumptions!D$29 | E13: =E4*Assumptions!E$29 | F13: =F4*Assumptions!F$29
A14: Less: Capital expenditures | B14: =B4*Assumptions!$B$30 | C14: =C4*Assumptions!$B$30 | D14: =D4*Assumptions!$B$30 | E14: =E4*Assumptions!$B$30 | F14: =F4*Assumptions!$B$30
A15: Less: Change in net working capital | B15: =(B4-Historicals!$E$4)*Assumptions!$B$31 | C15: =(C4-B4)*Assumptions!$B$31 | D15: =(D4-C4)*Assumptions!$B$31 | E15: =(E4-D4)*Assumptions!$B$31 | F15: =(F4-E4)*Assumptions!$B$31
A16: Unlevered free cash flow | B16: =B12+B8+B13-B14-B15 | C16: =C12+C8+C13-C14-C15 | D16: =D12+D8+D13-D14-D15 | E16: =E12+E8+E13-E14-E15 | F16: =F12+F8+F13-F14-F15
A17: Discount factor | B17: =1/(1+Assumptions!$B$16)^1 | C17: =1/(1+Assumptions!$B$16)^2 | D17: =1/(1+Assumptions!$B$16)^3 | E17: =1/(1+Assumptions!$B$16)^4 | F17: =1/(1+Assumptions!$B$16)^5
A18: Present value of FCF | B18: =B16*B17 | C18: =C16*C17 | D18: =D16*D17 | E18: =E16*E17 | F18: =F16*F17
A19: Sum of PV of FCF | B19: =SUM(B18:F18)
A20: Terminal value | B20: =F16*(1+Assumptions!$B$33)/(Assumptions!$B$16-Assumptions!$B$33)
A21: PV of terminal value | B21: =B20/(1+Assumptions!$B$16)^5
A22: Enterprise value | B22: =B19+B21
A23: Less: Net debt | B23: =Assumptions!$B$35
A24: Equity value | B24: =B22-B23
A25: Diluted shares outstanding (M) | B25: =Assumptions!$B$36
A26: Implied value per share ($) | B26: =B24/B25

Sheet DCF_Bear
A1: Broadcom Inc. (AVGO) — Discounted cash flow — bear case
A2: $ millions, except per-share. All formulas reference Assumptions / Historicals.
B3: 2026 | C3: 2027 | D3: 2028 | E3: 2029 | F3: 2030
A4: Revenue | B4: =Historicals!$E$4*(1+Assumptions!B$23) | C4: =B4*(1+Assumptions!C$23) | D4: =C4*(1+Assumptions!D$23) | E4: =D4*(1+Assumptions!E$23) | F4: =E4*(1+Assumptions!F$23)
A5: Revenue growth | B5: =B4/Historicals!$E$4-1 | C5: =C4/B4-1 | D5: =D4/C4-1 | E5: =E4/D4-1 | F5: =F4/E4-1
A6: EBITDA margin | B6: =Assumptions!B$26 | C6: =Assumptions!C$26 | D6: =Assumptions!D$26 | E6: =Assumptions!E$26 | F6: =Assumptions!F$26
A7: EBITDA | B7: =B4*B6 | C7: =C4*C6 | D7: =D4*D6 | E7: =E4*E6 | F7: =F4*F6
A8: Less: Depreciation & amortization | B8: =B4*Assumptions!$B$28 | C8: =C4*Assumptions!$B$28 | D8: =D4*Assumptions!$B$28 | E8: =E4*Assumptions!$B$28 | F8: =F4*Assumptions!$B$28
A9: EBIT | B9: =B7-B8 | C9: =C7-C8 | D9: =D7-D8 | E9: =E7-E8 | F9: =F7-F8
A10: Tax rate | B10: =Assumptions!$B$9 | C10: =Assumptions!$B$9 | D10: =Assumptions!$B$9 | E10: =Assumptions!$B$9 | F10: =Assumptions!$B$9
A11: Less: Income tax | B11: =B9*B10 | C11: =C9*C10 | D11: =D9*D10 | E11: =E9*E10 | F11: =F9*F10
A12: NOPAT | B12: =B9-B11 | C12: =C9-C11 | D12: =D9-D11 | E12: =E9-E11 | F12: =F9-F11
A13: Add: Stock-based compensation | B13: =B4*Assumptions!B$29 | C13: =C4*Assumptions!C$29 | D13: =D4*Assumptions!D$29 | E13: =E4*Assumptions!E$29 | F13: =F4*Assumptions!F$29
A14: Less: Capital expenditures | B14: =B4*Assumptions!$B$30 | C14: =C4*Assumptions!$B$30 | D14: =D4*Assumptions!$B$30 | E14: =E4*Assumptions!$B$30 | F14: =F4*Assumptions!$B$30
A15: Less: Change in net working capital | B15: =(B4-Historicals!$E$4)*Assumptions!$B$31 | C15: =(C4-B4)*Assumptions!$B$31 | D15: =(D4-C4)*Assumptions!$B$31 | E15: =(E4-D4)*Assumptions!$B$31 | F15: =(F4-E4)*Assumptions!$B$31
A16: Unlevered free cash flow | B16: =B12+B8+B13-B14-B15 | C16: =C12+C8+C13-C14-C15 | D16: =D12+D8+D13-D14-D15 | E16: =E12+E8+E13-E14-E15 | F16: =F12+F8+F13-F14-F15
A17: Discount factor | B17: =1/(1+Assumptions!$B$17)^1 | C17: =1/(1+Assumptions!$B$17)^2 | D17: =1/(1+Assumptions!$B$17)^3 | E17: =1/(1+Assumptions!$B$17)^4 | F17: =1/(1+Assumptions!$B$17)^5
A18: Present value of FCF | B18: =B16*B17 | C18: =C16*C17 | D18: =D16*D17 | E18: =E16*E17 | F18: =F16*F17
A19: Sum of PV of FCF | B19: =SUM(B18:F18)
A20: Terminal value | B20: =F16*(1+Assumptions!$B$34)/(Assumptions!$B$17-Assumptions!$B$34)
A21: PV of terminal value | B21: =B20/(1+Assumptions!$B$17)^5
A22: Enterprise value | B22: =B19+B21
A23: Less: Net debt | B23: =Assumptions!$B$35
A24: Equity value | B24: =B22-B23
A25: Diluted shares outstanding (M) | B25: =Assumptions!$B$36
A26: Implied value per share ($) | B26: =B24/B25

Sheet Comps
A1: Comparable companies — AI infrastructure & semiconductors
A2: Market data as of 2026-10-16 (Yahoo Finance, frozen in data/). $ millions, except price and per-share.
B3: AVGO | C3: NVDA | D3: AMD | E3: ALAB
A4: Price ($, Oct 16 close) | B4: 328.75 | C4: 214.13 | D4: 528.75 | E4: 285.82
A5: Market cap ($M) | B5: 1620074.6 | C5: 5278775.4 | D5: 902049.6 | E5: 50829.4
A6: Enterprise value ($M) | B6: 1604774.8 | C6: 5136924 | D6: 854336.2 | E6: 48377
A7: Revenue, TTM ($M) | B7: 89104 | C7: 302970 | D7: 41305 | E7: 1201.9
A8: EBITDA, TTM ($M) | B8: 52260 | C8: 201266 | D8: 9562 | E8: 285.4
A9: Forward EPS ($) | B9: 19.397 | C9: 15.9146 | D9: 15.7621 | E9: 6.4031
A10: EV / Revenue | B10: =B6/B7 | C10: =C6/C7 | D10: =D6/D7 | E10: =E6/E7
A11: EV / EBITDA | B11: =B6/B8 | C11: =C6/C8 | D11: =D6/D8 | E11: =E6/E8
A12: Trailing P/E | B12: 43.34 | C12: 27.64 | D12: 140.96 | E12: 144.33
A13: Forward P/E | B13: =B4/B9 | C13: =C4/C9 | D13: =D4/D9 | E13: =E4/E9
A15: AVGO implied valuation from peer multiples
A16: Median peer EV / Revenue | B16: =MEDIAN(C10:E10)
A17: Implied EV ($M) | B17: =B16*B7
A18: Less: Net debt ($M) | B18: =Assumptions!$B$35
A19: Implied equity ($M) | B19: =B17-B18
A20: Implied per share — EV/Revenue ($) | B20: =B19/Assumptions!$B$36 | C20: [JUDGMENT] Operative comps lens: EV/Revenue at median peer 20.7x → $378.60. Peer EV/EBITDA is distorted by AMD/ALAB growth-phase multiples.
A22: Median peer EV / EBITDA | B22: =MEDIAN(C11:E11)
A23: Implied EV ($M) | B23: =B22*B8
A24: Implied equity ($M) | B24: =B22-Assumptions!$B$35
A25: Implied per share — EV/EBITDA ($) | B25: =B24/Assumptions!$B$36 | C25: Shown for reference; median peer EV/EBITDA (89.3x) is dominated by AMD/ALAB growth-phase multiples — not the operative lens.
A27: Median peer forward P/E | B27: =MEDIAN(C13:F13)
A28: AVGO forward EPS ($) | B28: =B9
A29: Implied per share — forward P/E ($) | B29: =B27*B28 | C29: Forward P/E shown for reference; DCF is the primary lens.

Sheet Checks
A1: Verification appendix
A2: Tie-outs and data provenance. Every [DATA] input is sourced; every [JUDGMENT] input carries a rationale on Assumptions.
A3: Check | B3: Detail | C3: Status
A4: Net income ties across statements | B4: Cash-flow 'Net Income From Continuing Operations' = income-statement net income for FY2022–FY2025 (max diff $0.0M) | C4: PASS
A5: Revenue sourced from filings | B5: FY2022–FY2025 total revenue 33,203.0 / 35,819.0 / 51,574.0 / 63,887.0 ($M) from Yahoo Finance annual income statement; FY2021 column blank in source — excluded | C5: PASS
A6: Share count | B6: 4,773.6M outstanding (Yahoo Finance, Oct 2026); FY2025 diluted weighted avg 4,853M (10-K via Yahoo). Delta <2% | C6: PASS
A7: Net debt bridge | B7: Q3 FY2026 balance sheet (2026-07-31): total debt $59,419M less cash & equivalents $23,975M = net debt $35,444M | C7: PASS
A8: Beta | B8: 1.48 (Yahoo Finance 1.476, 2026-10-19); cross-checked MarketBeat 1.46, Finnhub 1.49 | C8: PASS
A9: Risk-free rate | B9: US 10Y 5.085% on 2026-10-19 (Reuters); used 5.1% — shared framework constant, already verified | C9: PASS
A10: Comps market data as-of | B10: NVDA / AVGO / AMD / ALAB Oct 16 closes and TTM fields pulled 2026-10-19 via Yahoo Finance (frozen in data/) | C10: PASS
A11: FCF bridge reconciles | B11: Formula check: EV = sum of PV of FCF + PV of terminal value | C11: =IF(ABS(DCF_Base!B22-(DCF_Base!B19+DCF_Base!B21))<0.5,"PASS","FAIL")
A12: Per-share arithmetic | B12: Formula check: per-share = equity value / shares | C12: =IF(ABS(DCF_Base!B26-DCF_Base!B24/DCF_Base!B25)<0.01,"PASS","FAIL")
A13: VMware amortization distorts GAAP net income | B13: FY2024 net income $5,895M vs EBITDA $23,879M — VMware intangibles amortization; model values on EBITDA/FCF, not GAAP NI | C13: PASS
A14: Tax normalization | B14: FY2025 tax provision was –$397M (benefit); model uses 21% statutory forward rate — flagged as judgment on Assumptions | C14: PASS
A15: Down-cycle in bear case | B15: Bear case includes an actual −12% revenue down year (FY2029), not just slower growth — semi cyclicality requirement | C15: PASS
A16: Dividend not modeled separately | B16: $0.65 quarterly dividend ($2.60 annualized, 0.8% yield) is cash returned within the enterprise framework — no double count | C16: PASS
A17: DCF vs market gap is explainable | B17: Base per-share trails $328.75 because an 11.5% WACC discounts even 24% 5-yr revenue CAGR hard; only the bull case (∼31% CAGR) reaches fair value — the market prices flawless execution | C17: PASS

Sheet Sources
A1: Sources
A2: Full URLs and access dates for every external input.
A3: # | B3: Source | C3: URL | D3: Accessed | E3: Used for
A4: 1 | B4: Yahoo Finance — AVGO quote & financials | C4: https://finance.yahoo.com/quote/AVGO | D4: 2026-10-19 | E4: Price, beta, shares, annual/quarterly statements (frozen in data/)
A5: 2 | B5: MarketBeat — AVGO stock analysis | C5: https://www.marketbeat.com/stocks/NASDAQ/AVGO/competitors-and-alternatives/ | D5: 2026-10-19 | E5: Beta (1.46) cross-check; price and earnings context
A6: 3 | B6: Finnhub — AVGO financial market data | C6: https://finnhub.io/?q=%22AVGO%22 | D6: 2026-10-19 | E6: Beta cross-check (1.49)
A7: 4 | B7: Reuters — 10Y yield 5.085% on Oct 19, 2026 | C7: https://www.reuters.com/business/wall-st-futures-climb-ai-stocks-rebound-oil-yields-fall-2026-10-19/ | D7: 2026-10-19 | E7: Risk-free rate (shared framework constant)
