Workbook

Sheet Cover
A1: Equity Research Teardown — Snowflake Inc. (NYSE: SNOW)
A2: Independent equity research project by Archit Chawla | As of October 19, 2026
A4: Current price (Oct 16, 2026 close) | B4: 306.84
A5: Recommendation | B5: PASS
A6: One-line thesis | B6: Never GAAP-profitable and priced as if profitability is assured: even modeling a full march to 18% EBITDA margins and 37% FCF margins, the DCF base sits ~57% below $306.84.
A8: Contents
A9: Assumptions | B9: WACC build and all forecast drivers; [DATA] vs [JUDGMENT] tags
A10: Historicals | B10: FY2023–FY2026 financials (fiscal year ends Jan 31) from Yahoo Finance annual statements
A11: DCF_Base / DCF_Bull / DCF_Bear | B11: 5-year DCF per case; all formulas live
A12: Comps | B12: CRM, NOW, PLTR multiples and SNOW-implied ranges
A13: Checks | B13: Verification appendix: tie-outs and data sources
A14: Sources | B14: Full URLs and access dates
A16: Disclaimer: Independent project for skill demonstration; not investment advice.

Sheet Assumptions
A1: Assumptions
A2: Blue cells are inputs. [DATA] = market/filing data; [JUDGMENT] = analyst estimate with rationale.
A3: WACC build
A4: Risk-free rate (US 10Y) | B4: 0.051 | C4: [DATA] | D4: 5.1% on 2026-10-19 (Reuters); verified for this project
A5: Equity risk premium | B5: 0.045 | C5: [JUDGMENT] | D5: Long-run US ERP assumption (shared framework)
A6: Beta (SNOW) | B6: 1.35 | C6: [DATA] | D6: Yahoo Finance 1.35 (2026-10-19); cross-checked 1.35 MarketBeat
A7: Cost of equity (CAPM) | B7: =Assumptions!$B$4+Assumptions!$B$6*Assumptions!$B$5 | C7: [CALC] | D7: Rf + beta × ERP
A8: Pre-tax cost of debt | B8: 0.055 | C8: [JUDGMENT] | D8: Convertible notes outstanding; 5.5% through-cycle new-issue estimate
A9: Marginal tax rate | B9: 0.21 | C9: [JUDGMENT] | D9: 21% statutory applied only when EBIT > 0 (formula floors tax at zero); EBIT is negative all five forecast years — NOL position, no cash taxes modeled
A10: After-tax cost of debt | B10: =Assumptions!$B$8*(1-Assumptions!$B$9) | C10: [CALC]
A11: Market value of equity ($M) | B11: 103558.5 | C11: [DATA] | D11: Oct 16 close $306.84 × 337.5M diluted shares = $103,559M
A12: Book value of debt ($M) | B12: 2763.8 | C12: [DATA] | D12: Q2 FY2027 balance sheet, 2026-07-31 (Yahoo Finance)
A13: Weight of equity | B13: =Assumptions!$B$11/(Assumptions!$B$11+Assumptions!$B$12) | C13: [CALC]
A14: Weight of debt | B14: =Assumptions!$B$12/(Assumptions!$B$11+Assumptions!$B$12) | C14: [CALC]
A15: WACC — base case | B15: =Assumptions!$B$13*Assumptions!$B$7+Assumptions!$B$14*Assumptions!$B$10 | C15: [CALC]
A16: WACC — bull case (-100 bps) | B16: =Assumptions!$B$15-0.01 | C16: [CALC] | D16: Rate-normalization scenario
A17: WACC — bear case (+100 bps) | B17: =Assumptions!$B$15+0.01 | C17: [CALC] | D17: Higher-for-longer scenario
A19: Forecast drivers (FY2027–FY2031 (fiscal; maps to calendar 2026–2030))
B20: FY2027 | C20: FY2028 | D20: FY2029 | E20: FY2030 | F20: FY2031
A21: Revenue growth — base | B21: 0.28 | C21: 0.25 | D21: 0.22 | E21: 0.2 | F21: 0.18 | G21: [JUDGMENT] | H21: Taper from 29.2% (FY2026); product-revenue guide ~25%+; consumption model
A22: Revenue growth — bull | B22: 0.33 | C22: 0.3 | D22: 0.27 | E22: 0.24 | F22: 0.21 | G22: [JUDGMENT] | H22: AI data-cloud workloads accelerate consumption growth
A23: Revenue growth — bear | B23: 0.22 | C23: 0.18 | D23: 0.15 | E23: 0.12 | F23: 0.1 | G23: [JUDGMENT] | H23: Consumption slowdown; hyperscaler competition
A24: EBITDA margin — base | B24: -0.15 | C24: -0.05 | D24: 0.05 | E24: 0.12 | F24: 0.18 | G24: [JUDGMENT] | H24: FY2026: –23.1%; path to +18% by FY2031 on operating leverage. Implies FCF-margin ramp 16.1% → 37.9% [JUDGMENT]
A25: EBITDA margin — bull | B25: -0.12 | C25: 0 | D25: 0.1 | E25: 0.17 | F25: 0.23 | G25: [JUDGMENT] | H25: Faster leverage; implies FCF margin 19.2% → 42.0%
A26: EBITDA margin — bear | B26: -0.18 | C26: -0.12 | D26: -0.05 | E26: 0.02 | F26: 0.08 | G26: [JUDGMENT] | H26: Slower leverage; implies FCF margin 12.9% → 29.7%
A28: D&A (% of revenue) | B28: 0.045 | G28: [JUDGMENT] | H28: FY2026 CF D&A $220M = 4.7% of revenue (IS row not broken out in source)
A29: Stock-based comp. (% of revenue) | B29: 0.32 | C29: 0.3 | D29: 0.28 | E29: 0.26 | F29: 0.24 | G29: [JUDGMENT] | H29: FY2026: 34.2% ($1,600M) — heaviest in the peer set; declining with scale; added back in the FCF bridge and disclosed
A30: Capex (% of revenue) | B30: 0.02 | G30: [JUDGMENT] | H30: FY2026: 2.2%
A31: Change in NWC (% of revenue growth) | B31: -0.05 | G31: [JUDGMENT] | H31: Negative = WC source: deferred-revenue tailwind; FY2026 dWC was +36% of revenue growth
A32: Terminal growth — base | B32: 0.03 | G32: [JUDGMENT] | H32: Long-run nominal GDP (shared framework)
A33: Terminal growth — bull | B33: 0.035 | G33: [JUDGMENT]
A34: Terminal growth — bear | B34: 0.02 | G34: [JUDGMENT]
A35: Net debt ($M) | B35: 1056.6 | G35: [DATA] | H35: Q2 FY2027: total debt $2,764M less cash $1,707M = net debt $1,057M
A36: Diluted shares outstanding (M) | B36: 337.5 | G36: [DATA] | H36: FY2026 diluted weighted average 337.5M (10-K via Yahoo); basic outstanding 352.8M per Yahoo

Sheet Historicals
A1: Historical financials — SNOW
A2: $ millions. Source: Yahoo Finance annual statements (filing-derived), as of 2026-10-19. FY2023–FY2026 (fiscal year ends Jan 31; all four years available in source).
B3: FY2023 | C3: FY2024 | D3: FY2025 | E3: FY2026
A4: Total revenue | B4: 2065.7 | C4: 2806.5 | D4: 3626.4 | E4: 4683.9
A5: Gross profit | B5: 1348.1 | C5: 1907.9 | D5: 2411.7 | E5: 3146.1
A6: EBITDA | B6: -752.5 | C6: -729.3 | D6: -1099.8 | E6: -1083.2
A7: EBITDA margin | B7: =B6/B4 | C7: =C6/C4 | D7: =D6/D4 | E7: =E6/E4
A8: Operating income | B8: -842.3 | C8: -1094.8 | D8: -1456 | E8: -1435.2
A9: Net income | B9: -796.7 | C9: -836.1 | D9: -1285.6 | E9: -1331.6
A10: Diluted average shares (M) | B10: 318.7 | C10: 328 | D10: 332.7 | E10: 337.5
A11: Operating cash flow | B11: 545.6 | C11: 848.1 | D11: 959.8 | E11: 1221.9
A12: Capital expenditures | B12: -49.8 | C12: -98 | D12: -75.7 | E12: -104.7
A13: Free cash flow | B13: 495.8 | C13: 750.2 | D13: 884.1 | E13: 1117.2
A14: Cash & equivalents | B14: 939.9 | C14: 1762.7 | D14: 2628.8 | E14: 2828.2
A15: Total debt | B15: 251.7 | C15: 288 | D15: 2685.3 | E15: 2741.1
A16: Revenue growth | C16: =C4/B4-1 | D16: =D4/C4-1 | E16: =E4/D4-1

Sheet DCF_Base
A1: Snowflake Inc. (SNOW) — Discounted cash flow — base case
A2: $ millions, except per-share. All formulas reference Assumptions / Historicals.
B3: FY2027 | C3: FY2028 | D3: FY2029 | E3: FY2030 | F3: FY2031
A4: Revenue | B4: =Historicals!$E$4*(1+Assumptions!B$21) | C4: =B4*(1+Assumptions!C$21) | D4: =C4*(1+Assumptions!D$21) | E4: =D4*(1+Assumptions!E$21) | F4: =E4*(1+Assumptions!F$21)
A5: Revenue growth | B5: =B4/Historicals!$E$4-1 | C5: =C4/B4-1 | D5: =D4/C4-1 | E5: =E4/D4-1 | F5: =F4/E4-1
A6: EBITDA margin | B6: =Assumptions!B$24 | C6: =Assumptions!C$24 | D6: =Assumptions!D$24 | E6: =Assumptions!E$24 | F6: =Assumptions!F$24
A7: EBITDA | B7: =B4*B6 | C7: =C4*C6 | D7: =D4*D6 | E7: =E4*E6 | F7: =F4*F6
A8: Less: Depreciation & amortization | B8: =B4*Assumptions!$B$28 | C8: =C4*Assumptions!$B$28 | D8: =D4*Assumptions!$B$28 | E8: =E4*Assumptions!$B$28 | F8: =F4*Assumptions!$B$28
A9: EBIT | B9: =B7-B8 | C9: =C7-C8 | D9: =D7-D8 | E9: =E7-E8 | F9: =F7-F8
A10: Tax rate | B10: =Assumptions!$B$9 | C10: =Assumptions!$B$9 | D10: =Assumptions!$B$9 | E10: =Assumptions!$B$9 | F10: =Assumptions!$B$9
A11: Less: Income tax | B11: =MAX(B9,0)*B10 | C11: =MAX(C9,0)*C10 | D11: =MAX(D9,0)*D10 | E11: =MAX(E9,0)*E10 | F11: =MAX(F9,0)*F10
A12: NOPAT | B12: =B9-B11 | C12: =C9-C11 | D12: =D9-D11 | E12: =E9-E11 | F12: =F9-F11
A13: Add: Stock-based compensation | B13: =B4*Assumptions!B$29 | C13: =C4*Assumptions!C$29 | D13: =D4*Assumptions!D$29 | E13: =E4*Assumptions!E$29 | F13: =F4*Assumptions!F$29
A14: Less: Capital expenditures | B14: =B4*Assumptions!$B$30 | C14: =C4*Assumptions!$B$30 | D14: =D4*Assumptions!$B$30 | E14: =E4*Assumptions!$B$30 | F14: =F4*Assumptions!$B$30
A15: Less: Change in net working capital | B15: =(B4-Historicals!$E$4)*Assumptions!$B$31 | C15: =(C4-B4)*Assumptions!$B$31 | D15: =(D4-C4)*Assumptions!$B$31 | E15: =(E4-D4)*Assumptions!$B$31 | F15: =(F4-E4)*Assumptions!$B$31
A16: Unlevered free cash flow | B16: =B12+B8+B13-B14-B15 | C16: =C12+C8+C13-C14-C15 | D16: =D12+D8+D13-D14-D15 | E16: =E12+E8+E13-E14-E15 | F16: =F12+F8+F13-F14-F15
A17: Discount factor | B17: =1/(1+Assumptions!$B$15)^1 | C17: =1/(1+Assumptions!$B$15)^2 | D17: =1/(1+Assumptions!$B$15)^3 | E17: =1/(1+Assumptions!$B$15)^4 | F17: =1/(1+Assumptions!$B$15)^5
A18: Present value of FCF | B18: =B16*B17 | C18: =C16*C17 | D18: =D16*D17 | E18: =E16*E17 | F18: =F16*F17
A19: Sum of PV of FCF | B19: =SUM(B18:F18)
A20: Terminal value | B20: =F16*(1+Assumptions!$B$32)/(Assumptions!$B$15-Assumptions!$B$32)
A21: PV of terminal value | B21: =B20/(1+Assumptions!$B$15)^5
A22: Enterprise value | B22: =B19+B21
A23: Less: Net debt | B23: =Assumptions!$B$35
A24: Equity value | B24: =B22-B23
A25: Diluted shares outstanding (M) | B25: =Assumptions!$B$36
A26: Implied value per share ($) | B26: =B24/B25

Sheet DCF_Bull
A1: Snowflake Inc. (SNOW) — Discounted cash flow — bull case
A2: $ millions, except per-share. All formulas reference Assumptions / Historicals.
B3: FY2027 | C3: FY2028 | D3: FY2029 | E3: FY2030 | F3: FY2031
A4: Revenue | B4: =Historicals!$E$4*(1+Assumptions!B$22) | C4: =B4*(1+Assumptions!C$22) | D4: =C4*(1+Assumptions!D$22) | E4: =D4*(1+Assumptions!E$22) | F4: =E4*(1+Assumptions!F$22)
A5: Revenue growth | B5: =B4/Historicals!$E$4-1 | C5: =C4/B4-1 | D5: =D4/C4-1 | E5: =E4/D4-1 | F5: =F4/E4-1
A6: EBITDA margin | B6: =Assumptions!B$25 | C6: =Assumptions!C$25 | D6: =Assumptions!D$25 | E6: =Assumptions!E$25 | F6: =Assumptions!F$25
A7: EBITDA | B7: =B4*B6 | C7: =C4*C6 | D7: =D4*D6 | E7: =E4*E6 | F7: =F4*F6
A8: Less: Depreciation & amortization | B8: =B4*Assumptions!$B$28 | C8: =C4*Assumptions!$B$28 | D8: =D4*Assumptions!$B$28 | E8: =E4*Assumptions!$B$28 | F8: =F4*Assumptions!$B$28
A9: EBIT | B9: =B7-B8 | C9: =C7-C8 | D9: =D7-D8 | E9: =E7-E8 | F9: =F7-F8
A10: Tax rate | B10: =Assumptions!$B$9 | C10: =Assumptions!$B$9 | D10: =Assumptions!$B$9 | E10: =Assumptions!$B$9 | F10: =Assumptions!$B$9
A11: Less: Income tax | B11: =MAX(B9,0)*B10 | C11: =MAX(C9,0)*C10 | D11: =MAX(D9,0)*D10 | E11: =MAX(E9,0)*E10 | F11: =MAX(F9,0)*F10
A12: NOPAT | B12: =B9-B11 | C12: =C9-C11 | D12: =D9-D11 | E12: =E9-E11 | F12: =F9-F11
A13: Add: Stock-based compensation | B13: =B4*Assumptions!B$29 | C13: =C4*Assumptions!C$29 | D13: =D4*Assumptions!D$29 | E13: =E4*Assumptions!E$29 | F13: =F4*Assumptions!F$29
A14: Less: Capital expenditures | B14: =B4*Assumptions!$B$30 | C14: =C4*Assumptions!$B$30 | D14: =D4*Assumptions!$B$30 | E14: =E4*Assumptions!$B$30 | F14: =F4*Assumptions!$B$30
A15: Less: Change in net working capital | B15: =(B4-Historicals!$E$4)*Assumptions!$B$31 | C15: =(C4-B4)*Assumptions!$B$31 | D15: =(D4-C4)*Assumptions!$B$31 | E15: =(E4-D4)*Assumptions!$B$31 | F15: =(F4-E4)*Assumptions!$B$31
A16: Unlevered free cash flow | B16: =B12+B8+B13-B14-B15 | C16: =C12+C8+C13-C14-C15 | D16: =D12+D8+D13-D14-D15 | E16: =E12+E8+E13-E14-E15 | F16: =F12+F8+F13-F14-F15
A17: Discount factor | B17: =1/(1+Assumptions!$B$16)^1 | C17: =1/(1+Assumptions!$B$16)^2 | D17: =1/(1+Assumptions!$B$16)^3 | E17: =1/(1+Assumptions!$B$16)^4 | F17: =1/(1+Assumptions!$B$16)^5
A18: Present value of FCF | B18: =B16*B17 | C18: =C16*C17 | D18: =D16*D17 | E18: =E16*E17 | F18: =F16*F17
A19: Sum of PV of FCF | B19: =SUM(B18:F18)
A20: Terminal value | B20: =F16*(1+Assumptions!$B$33)/(Assumptions!$B$16-Assumptions!$B$33)
A21: PV of terminal value | B21: =B20/(1+Assumptions!$B$16)^5
A22: Enterprise value | B22: =B19+B21
A23: Less: Net debt | B23: =Assumptions!$B$35
A24: Equity value | B24: =B22-B23
A25: Diluted shares outstanding (M) | B25: =Assumptions!$B$36
A26: Implied value per share ($) | B26: =B24/B25

Sheet DCF_Bear
A1: Snowflake Inc. (SNOW) — Discounted cash flow — bear case
A2: $ millions, except per-share. All formulas reference Assumptions / Historicals.
B3: FY2027 | C3: FY2028 | D3: FY2029 | E3: FY2030 | F3: FY2031
A4: Revenue | B4: =Historicals!$E$4*(1+Assumptions!B$23) | C4: =B4*(1+Assumptions!C$23) | D4: =C4*(1+Assumptions!D$23) | E4: =D4*(1+Assumptions!E$23) | F4: =E4*(1+Assumptions!F$23)
A5: Revenue growth | B5: =B4/Historicals!$E$4-1 | C5: =C4/B4-1 | D5: =D4/C4-1 | E5: =E4/D4-1 | F5: =F4/E4-1
A6: EBITDA margin | B6: =Assumptions!B$26 | C6: =Assumptions!C$26 | D6: =Assumptions!D$26 | E6: =Assumptions!E$26 | F6: =Assumptions!F$26
A7: EBITDA | B7: =B4*B6 | C7: =C4*C6 | D7: =D4*D6 | E7: =E4*E6 | F7: =F4*F6
A8: Less: Depreciation & amortization | B8: =B4*Assumptions!$B$28 | C8: =C4*Assumptions!$B$28 | D8: =D4*Assumptions!$B$28 | E8: =E4*Assumptions!$B$28 | F8: =F4*Assumptions!$B$28
A9: EBIT | B9: =B7-B8 | C9: =C7-C8 | D9: =D7-D8 | E9: =E7-E8 | F9: =F7-F8
A10: Tax rate | B10: =Assumptions!$B$9 | C10: =Assumptions!$B$9 | D10: =Assumptions!$B$9 | E10: =Assumptions!$B$9 | F10: =Assumptions!$B$9
A11: Less: Income tax | B11: =MAX(B9,0)*B10 | C11: =MAX(C9,0)*C10 | D11: =MAX(D9,0)*D10 | E11: =MAX(E9,0)*E10 | F11: =MAX(F9,0)*F10
A12: NOPAT | B12: =B9-B11 | C12: =C9-C11 | D12: =D9-D11 | E12: =E9-E11 | F12: =F9-F11
A13: Add: Stock-based compensation | B13: =B4*Assumptions!B$29 | C13: =C4*Assumptions!C$29 | D13: =D4*Assumptions!D$29 | E13: =E4*Assumptions!E$29 | F13: =F4*Assumptions!F$29
A14: Less: Capital expenditures | B14: =B4*Assumptions!$B$30 | C14: =C4*Assumptions!$B$30 | D14: =D4*Assumptions!$B$30 | E14: =E4*Assumptions!$B$30 | F14: =F4*Assumptions!$B$30
A15: Less: Change in net working capital | B15: =(B4-Historicals!$E$4)*Assumptions!$B$31 | C15: =(C4-B4)*Assumptions!$B$31 | D15: =(D4-C4)*Assumptions!$B$31 | E15: =(E4-D4)*Assumptions!$B$31 | F15: =(F4-E4)*Assumptions!$B$31
A16: Unlevered free cash flow | B16: =B12+B8+B13-B14-B15 | C16: =C12+C8+C13-C14-C15 | D16: =D12+D8+D13-D14-D15 | E16: =E12+E8+E13-E14-E15 | F16: =F12+F8+F13-F14-F15
A17: Discount factor | B17: =1/(1+Assumptions!$B$17)^1 | C17: =1/(1+Assumptions!$B$17)^2 | D17: =1/(1+Assumptions!$B$17)^3 | E17: =1/(1+Assumptions!$B$17)^4 | F17: =1/(1+Assumptions!$B$17)^5
A18: Present value of FCF | B18: =B16*B17 | C18: =C16*C17 | D18: =D16*D17 | E18: =E16*E17 | F18: =F16*F17
A19: Sum of PV of FCF | B19: =SUM(B18:F18)
A20: Terminal value | B20: =F16*(1+Assumptions!$B$34)/(Assumptions!$B$17-Assumptions!$B$34)
A21: PV of terminal value | B21: =B20/(1+Assumptions!$B$17)^5
A22: Enterprise value | B22: =B19+B21
A23: Less: Net debt | B23: =Assumptions!$B$35
A24: Equity value | B24: =B22-B23
A25: Diluted shares outstanding (M) | B25: =Assumptions!$B$36
A26: Implied value per share ($) | B26: =B24/B25

Sheet Comps
A1: Comparable companies — enterprise SaaS
A2: Market data as of 2026-10-16 (Oct 16 closes via Yahoo Finance). $ millions, except price and per-share. EV uses Oct 16 market cap + latest-quarter total debt less cash. SNOW EBITDA is negative — EV/EBITDA n/a.
B3: SNOW | C3: CRM | D3: NOW | E3: PLTR
A4: Price ($) | B4: 306.84 | C4: 240.7 | D4: 141.97 | E4: 186.03
A5: Market cap ($M) | B5: 108253.2 | C5: 198096.1 | D5: 146777.7 | E5: 427999.4
A6: Enterprise value ($M) | B6: 109309.8 | C6: 231529.1 | D6: 152727.7 | E6: 426180.8
A7: Revenue, TTM ($M) | B7: 5434.6 | C7: 43938 | D7: 14732 | E7: 6155.9
A8: EBITDA, TTM ($M) | B8: -1036.3 | C8: 12899 | D8: 2897 | E8: 2662.6
A9: Forward EPS ($) | B9: 3.008 | C9: 16.023 | D9: 5.005 | E9: 2.352
A10: EV / Revenue | B10: =B6/B7 | C10: =C6/C7 | D10: =D6/D7 | E10: =E6/E7
A11: EV / EBITDA | B11: n/a | C11: =C6/C8 | D11: =D6/D8 | E11: =E6/E8
A12: Trailing P/E | B12: n/a | C12: 21.98 | D12: 88.73 | E12: 160.37
A13: Forward P/E | B13: =B4/B9 | C13: =C4/C9 | D13: =D4/D9 | E13: =E4/E9
A15: SNOW implied valuation from peer multiples
A16: Median peer EV / Revenue | B16: =MEDIAN(C10:E10)
A17: Implied EV ($M) | B17: =B16*B7
A18: Less: Net debt ($M) | B18: =Assumptions!$B$35
A19: Implied equity ($M) | B19: =B17-B18
A20: Implied per share — EV/Revenue ($) | B20: =B19/Assumptions!$B$36 | C20: Reference only: PLTR's 69x sales skews the median upward; CRM's 5.3x is the mature anchor.
A22: Median peer forward P/E | B22: =MEDIAN(C13:E13)
A23: SNOW forward EPS ($) | B23: =B9
A24: Implied per share — forward P/E ($) | B24: =B22*B23 | C24: Treat with caution: SNOW forward EPS is non-GAAP (excludes ~30% SBC); GAAP P/E is negative.

Sheet Checks
A1: Verification appendix
A2: Tie-outs and data provenance. Every [DATA] input is sourced; every [JUDGMENT] input carries a rationale on Assumptions.
A3: Check | B3: Detail | C3: Status
A4: Net income ties across statements | B4: Income-statement vs cash-flow-statement net income for FY2023–FY2026 (max diff $3.6M on ~$1.3B losses — rounding/minority interest) | C4: PASS
A5: Revenue sourced from filings | B5: FY2023–FY2026 total revenue 2,065.7 / 2,806.5 / 3,626.4 / 4,683.9 ($M) | C5: PASS
A6: Never GAAP-profitable — flagged | B6: Net income negative every reported year (FY2026: –$1,332M); DCF runs on a revenue → FCF-margin path: FCF margin ramps 16.1% → 37.9% base case via the bridge (SBC add-back disclosed) | C6: PASS
A7: SBC magnitude | B7: FY2026 SBC $1,600M = 34.2% of revenue — heaviest in the peer set; added back in the FCF bridge; valuation is sensitive to the SBC decline path | C7: PASS
A8: Tax floor | B8: Formula applies MAX(EBIT,0) × 21%: EBIT is negative all five forecast years, so no income tax is modeled — consistent with the NOL position | C8: PASS
A9: Share count | B9: 337.5M diluted weighted avg (FY2026 10-K via Yahoo); basic outstanding 352.8M per Yahoo | C9: PASS
A10: Net debt bridge | B10: Q2 FY2027 balance sheet (2026-07-31): total debt $2,763.8M less cash $1,707.2M = net debt $1,056.6M | C10: PASS
A11: Beta | B11: 1.35 used; Yahoo Finance 1.35 (2026-10-19); cross-checked 1.35 MarketBeat | C11: PASS
A12: Risk-free rate | B12: US 10Y 5.1% on 2026-10-19 (Reuters) — shared framework input | C12: PASS
A13: Fiscal year | B13: SNOW fiscal year ends Jan 31: historicals FY2023–FY2026, forecast FY2027–FY2031 (maps to calendar 2026–2030) | C13: PASS
A14: DCF vs market gap is explainable | B14: Base per-share trails $306.84 by ~57%: even a full march to 18% EBITDA / 37% FCF margins cannot support the quote at an 11.0% WACC — the market prices flawless AI data-cloud execution | C14: PASS
A15: Comps market data as-of | B15: CRM / NOW / SNOW / PLTR Oct 16 closes and TTM financials pulled 2026-10-19 via Yahoo Finance | C15: PASS
A16: FCF bridge reconciles | B16: Formula check: EV = sum of PV of FCF + PV of terminal value | C16: =IF(ABS(DCF_Base!B22-(DCF_Base!B19+DCF_Base!B21))<0.5,"PASS","FAIL")
A17: Per-share arithmetic | B17: Formula check: per-share = equity value / shares | C17: =IF(ABS(DCF_Base!B26-DCF_Base!B24/DCF_Base!B25)<0.01,"PASS","FAIL")

Sheet Sources
A1: Sources
A2: Full URLs and access dates for every external input.
A3: # | B3: Source | C3: URL | D3: Accessed | E3: Used for
A4: 1 | B4: Yahoo Finance — SNOW quote & financials | C4: https://finance.yahoo.com/quote/SNOW | D4: 2026-10-19 | E4: quote & financials
A5: 2 | B5: Yahoo Finance — CRM comps market data | C5: https://finance.yahoo.com/quote/CRM | D5: 2026-10-19 | E5: comps market data
A6: 3 | B6: Yahoo Finance — NOW comps market data | C6: https://finance.yahoo.com/quote/NOW | D6: 2026-10-19 | E6: comps market data
A7: 4 | B7: Yahoo Finance — PLTR comps market data | C7: https://finance.yahoo.com/quote/PLTR | D7: 2026-10-19 | E7: comps market data
A8: 5 | B8: Reuters — 10Y yield 5.085% on Oct 19, 2026 | C8: https://www.reuters.com/business/wall-st-futures-climb-ai-stocks-rebound-oil-yields-fall-2026-10-19/ | D8: 2026-10-19 | E8: Risk-free rate (5.1%)
A9: 6 | B9: MarketBeat — SNOW | C9: https://www.marketbeat.com/stocks/NYSE/SNOW/ | D9: 2026-10-19 | E9: Beta (1.35) cross-check; profitability context
A10: 7 | B10: A.L. Capital Advisory — SNOW | C10: https://alcapitaladvisory.com/research/equities/snow.html | D10: 2026-10-19 | E10: Beta (1.35) context
