Workbook

Sheet Cover
A1: Equity Research Teardown — JPMorgan Chase & Co. (NYSE: JPM)
A2: Independent equity research project by Archit Chawla | As of October 19, 2026
A4: Current price (Oct 16, 2026 close) | B4: 339.72
A5: Recommendation | B5: HOLD
A6: One-line thesis | B6: The fortress balance sheet of American banking, fairly priced: DCF base sits 8% below the quote while peer multiples say fair value.
A8: Contents
A9: Assumptions | B9: Cost-of-equity build and all forecast drivers; [DATA] vs [JUDGMENT] tags
A10: Historicals | B10: FY2022–2025 financials from Yahoo Finance annual statements
A11: DCF_Base / DCF_Bull / DCF_Bear | B11: 5-year distributable-cash-flow DCF per case; all formulas live
A12: Comps | B12: JPM, GS, MS, BLK multiples (P/E and P/B) and implied ranges
A13: Checks | B13: Verification appendix: tie-outs and data sources
A14: Sources | B14: Full URLs and access dates
A16: Disclaimer: Independent project for skill demonstration; not investment advice.

Sheet Assumptions
A1: Assumptions
A2: Blue cells are inputs. [DATA] = market/filing data; [JUDGMENT] = analyst estimate with rationale.
A3: Cost of equity build
A4: Risk-free rate (US 10Y) | B4: 0.051 | C4: [DATA] | D4: 5.09% on 2026-10-19 (Reuters); rounded to 5.1%
A5: Equity risk premium | B5: 0.045 | C5: [JUDGMENT] | D5: Long-run US ERP assumption
A6: Beta (JPM) | B6: 1.02 | C6: [DATA] | D6: Yahoo Finance 1.015 (2026-10-19); Finnhub 1.04; alcapitaladvisory 1.01; MarketBeat 1.02. Used 1.02
A7: Cost of equity (CAPM) | B7: =Assumptions!$B$4+Assumptions!$B$6*Assumptions!$B$5 | C7: [CALC] | D7: Rf + beta × ERP; no debt weighting (bank framework)
A8: Cost of equity — bull case (-100 bps) | B8: =Assumptions!$B$7-0.01 | C8: [CALC] | D8: Rate-normalization scenario
A9: Cost of equity — bear case (+100 bps) | B9: =Assumptions!$B$7+0.01 | C9: [CALC] | D9: Higher-for-longer scenario
A11: Framework adaptation (bank DCF)
A12: Framework adaptation: banks cannot be valued on enterprise FCF/WACC — leverage is the product, and book debt has no clean market value. I value equity directly: forecast net income (FY2026–2030), apply a total payout ratio (common dividends + share buybacks) to get distributable cash flow, and discount at cost of equity (5.1% US 10Y + beta × 4.5% ERP, no debt weighting). Terminal value is a single-stage Gordon on 2030 distributable cash flow at 3.0% perpetual growth (bull 3.5%, bear 2.0%); bull/bear cost of equity ∓100/ +100 bps. This is the standard dividend-discount / FCFE approach for financials.
A15: Forecast drivers (2026–2030)
B16: 2026 | C16: 2027 | D16: 2028 | E16: 2029 | F16: 2030
A17: Net income growth — base | B17: 0.03 | C17: 0.05 | D17: 0.05 | E17: 0.04 | F17: 0.03 | G17: [JUDGMENT] | H17: 3.0% NI CAGR FY2025-30; card/market normalization in outer years
A18: Net income growth — bull | B18: 0.08 | C18: 0.1 | D18: 0.08 | E18: 0.07 | F18: 0.05 | G18: [JUDGMENT] | H18: Capital-markets supercycle / AI deal wave
A19: Net income growth — bear | B19: -0.12 | C19: -0.06 | D19: 0 | E19: 0.02 | F19: 0.03 | G19: [JUDGMENT] | H19: Rate normalization compresses NII; credit costs rise
A20: Dividend payout ratio — base | B20: 0.3 | C20: 0.3 | D20: 0.31 | E20: 0.31 | F20: 0.31 | G20: [JUDGMENT] | H20: ~93% total payout: ~30% dividend + ~63% buyback; matches 2025 actual 90.0%
A21: Dividend payout ratio — bull | B21: 0.3 | C21: 0.3 | D21: 0.3 | E21: 0.3 | F21: 0.3 | G21: [JUDGMENT] | H21: Dividend held steady; buybacks take the upside
A22: Dividend payout ratio — bear | B22: 0.32 | C22: 0.32 | D22: 0.32 | E22: 0.32 | F22: 0.32 | G22: [JUDGMENT] | H22: Dividend defended; buybacks cut
A23: Buyback payout ratio — base | B23: 0.62 | C23: 0.63 | D23: 0.63 | E23: 0.62 | F23: 0.62 | G23: [JUDGMENT] | H23: 3-yr granular FY2026-28; steady-state glide FY2029-30
A24: Buyback payout ratio — bull | B24: 0.7 | C24: 0.7 | D24: 0.7 | E24: 0.7 | F24: 0.7 | G24: [JUDGMENT] | H24: Excess capital returned aggressively
A25: Buyback payout ratio — bear | B25: 0.48 | C25: 0.48 | D25: 0.48 | E25: 0.48 | F25: 0.48 | G25: [JUDGMENT] | H25: Capital conserved under stress
A27: Terminal growth — base | B27: 0.03 | G27: [JUDGMENT] | H27: Long-run nominal GDP
A28: Terminal growth — bull | B28: 0.035 | G28: [JUDGMENT]
A29: Terminal growth — bear | B29: 0.02 | G29: [JUDGMENT]
A30: FY2025 net income, common ($M) | B30: 55681 | G30: [DATA] | H30: Yahoo Finance annual income statement
A31: FY2025 preferred stock dividends ($M) | B31: 1099 | G31: [DATA] | H31: Subtracted in the distribution bridge
A32: Shares outstanding (M) | B32: 2655.6 | G32: [DATA] | H32: Yahoo Finance, Oct 2026; Oct 16 mkt cap = price × shares

Sheet Historicals
A1: Historical financials — JPM
A2: $ millions, except per-share. Source: Yahoo Finance annual statements (filing-derived), as of 2026-10-19.
B3: 2022 | C3: 2023 | D3: 2024 | E3: 2025
A4: Total revenue | B4: 127727 | C4: 154952 | D4: 169439 | E4: 181847
A5: Net interest income | B5: 66710 | C5: 89267 | D5: 92583 | E5: 95443
A6: Net income, common stockholders | B6: 35892 | C6: 47760 | D6: 56868 | E6: 55681
A7: Preferred stock dividends | B7: 1595 | C7: 1501 | D7: 1259 | E7: 1099
A8: Cash dividends paid | B8: 13562 | C8: 13463 | D8: 14783 | E8: 16625
A9: Share repurchases | B9: 10596 | C9: 9824 | D9: 28680 | E9: 34591
A10: Total distributions to common | B10: =B8+B9-B7 | C10: =C8+C9-C7 | D10: =D8+D9-D7 | E10: =E8+E9-E7
A11: Total payout ratio | B11: =B10/B6 | C11: =C10/C6 | D11: =D10/D6 | E11: =E10/E6
A12: Diluted average shares (M) | B12: 2970 | C12: 2943.1 | D12: 2879 | E12: 2781.5
A13: Common stockholders' equity | B13: 264928 | C13: 300474 | D13: 324708 | E13: 342393
A14: ROE (NI common / common equity) | B14: =B6/B13 | C14: =C6/C13 | D14: =D6/D13 | E14: =E6/E13
A15: Ordinary shares outstanding (M) | B15: 2934.3 | C15: 2876.7 | D15: 2797.6 | E15: 2696.3
A16: Book value per share ($) | B16: =B13/B15 | C16: =C13/C15 | D16: =D13/D15 | E16: =E13/E15

Sheet DCF_Base
A1: JPMorgan Chase & Co. (JPM) — Distributable-cash-flow DCF — base case
A2: $ millions, except per-share. All formulas reference Assumptions / Historicals.
B3: 2026 | C3: 2027 | D3: 2028 | E3: 2029 | F3: 2030
A4: Net income, common stockholders | B4: =Assumptions!$B$30*(1+Assumptions!B$17) | C4: =B4*(1+Assumptions!C$17) | D4: =C4*(1+Assumptions!D$17) | E4: =D4*(1+Assumptions!E$17) | F4: =E4*(1+Assumptions!F$17)
A5: Net income growth | B5: =B4/Assumptions!$B$30-1 | C5: =C4/B4-1 | D5: =D4/C4-1 | E5: =E4/D4-1 | F5: =F4/E4-1
A6: Dividend payout ratio | B6: =Assumptions!B$20 | C6: =Assumptions!C$20 | D6: =Assumptions!D$20 | E6: =Assumptions!E$20 | F6: =Assumptions!F$20
A7: Common dividends | B7: =B4*B6 | C7: =C4*C6 | D7: =D4*D6 | E7: =E4*E6 | F7: =F4*F6
A8: Buyback payout ratio | B8: =Assumptions!B$23 | C8: =Assumptions!C$23 | D8: =Assumptions!D$23 | E8: =Assumptions!E$23 | F8: =Assumptions!F$23
A9: Share repurchases | B9: =B4*B8 | C9: =C4*C8 | D9: =D4*D8 | E9: =E4*E8 | F9: =F4*F8
A10: Total distributable cash flow | B10: =B7+B9 | C10: =C7+C9 | D10: =D7+D9 | E10: =E7+E9 | F10: =F7+F9
A11: Discount factor | B11: =1/(1+Assumptions!$B$7)^1 | C11: =1/(1+Assumptions!$B$7)^2 | D11: =1/(1+Assumptions!$B$7)^3 | E11: =1/(1+Assumptions!$B$7)^4 | F11: =1/(1+Assumptions!$B$7)^5
A12: Present value of distrib. CF | B12: =B10*B11 | C12: =C10*C11 | D12: =D10*D11 | E12: =E10*E11 | F12: =F10*F11
A14: Sum of PV of distributable CF | B14: =SUM(B12:F12)
A15: Terminal value (Gordon on 2030 distrib. CF) | B15: =F10*(1+Assumptions!$B$27)/(Assumptions!$B$7-Assumptions!$B$27)
A16: PV of terminal value | B16: =B15/(1+Assumptions!$B$7)^5
A17: Equity value | B17: =B14+B16
A18: Shares outstanding (M) | B18: =Assumptions!$B$32
A19: Implied value per share ($) | B19: =B17/B18

Sheet DCF_Bull
A1: JPMorgan Chase & Co. (JPM) — Distributable-cash-flow DCF — bull case
A2: $ millions, except per-share. All formulas reference Assumptions / Historicals.
B3: 2026 | C3: 2027 | D3: 2028 | E3: 2029 | F3: 2030
A4: Net income, common stockholders | B4: =Assumptions!$B$30*(1+Assumptions!B$18) | C4: =B4*(1+Assumptions!C$18) | D4: =C4*(1+Assumptions!D$18) | E4: =D4*(1+Assumptions!E$18) | F4: =E4*(1+Assumptions!F$18)
A5: Net income growth | B5: =B4/Assumptions!$B$30-1 | C5: =C4/B4-1 | D5: =D4/C4-1 | E5: =E4/D4-1 | F5: =F4/E4-1
A6: Dividend payout ratio | B6: =Assumptions!B$21 | C6: =Assumptions!C$21 | D6: =Assumptions!D$21 | E6: =Assumptions!E$21 | F6: =Assumptions!F$21
A7: Common dividends | B7: =B4*B6 | C7: =C4*C6 | D7: =D4*D6 | E7: =E4*E6 | F7: =F4*F6
A8: Buyback payout ratio | B8: =Assumptions!B$24 | C8: =Assumptions!C$24 | D8: =Assumptions!D$24 | E8: =Assumptions!E$24 | F8: =Assumptions!F$24
A9: Share repurchases | B9: =B4*B8 | C9: =C4*C8 | D9: =D4*D8 | E9: =E4*E8 | F9: =F4*F8
A10: Total distributable cash flow | B10: =B7+B9 | C10: =C7+C9 | D10: =D7+D9 | E10: =E7+E9 | F10: =F7+F9
A11: Discount factor | B11: =1/(1+Assumptions!$B$8)^1 | C11: =1/(1+Assumptions!$B$8)^2 | D11: =1/(1+Assumptions!$B$8)^3 | E11: =1/(1+Assumptions!$B$8)^4 | F11: =1/(1+Assumptions!$B$8)^5
A12: Present value of distrib. CF | B12: =B10*B11 | C12: =C10*C11 | D12: =D10*D11 | E12: =E10*E11 | F12: =F10*F11
A14: Sum of PV of distributable CF | B14: =SUM(B12:F12)
A15: Terminal value (Gordon on 2030 distrib. CF) | B15: =F10*(1+Assumptions!$B$28)/(Assumptions!$B$8-Assumptions!$B$28)
A16: PV of terminal value | B16: =B15/(1+Assumptions!$B$8)^5
A17: Equity value | B17: =B14+B16
A18: Shares outstanding (M) | B18: =Assumptions!$B$32
A19: Implied value per share ($) | B19: =B17/B18

Sheet DCF_Bear
A1: JPMorgan Chase & Co. (JPM) — Distributable-cash-flow DCF — bear case
A2: $ millions, except per-share. All formulas reference Assumptions / Historicals.
B3: 2026 | C3: 2027 | D3: 2028 | E3: 2029 | F3: 2030
A4: Net income, common stockholders | B4: =Assumptions!$B$30*(1+Assumptions!B$19) | C4: =B4*(1+Assumptions!C$19) | D4: =C4*(1+Assumptions!D$19) | E4: =D4*(1+Assumptions!E$19) | F4: =E4*(1+Assumptions!F$19)
A5: Net income growth | B5: =B4/Assumptions!$B$30-1 | C5: =C4/B4-1 | D5: =D4/C4-1 | E5: =E4/D4-1 | F5: =F4/E4-1
A6: Dividend payout ratio | B6: =Assumptions!B$22 | C6: =Assumptions!C$22 | D6: =Assumptions!D$22 | E6: =Assumptions!E$22 | F6: =Assumptions!F$22
A7: Common dividends | B7: =B4*B6 | C7: =C4*C6 | D7: =D4*D6 | E7: =E4*E6 | F7: =F4*F6
A8: Buyback payout ratio | B8: =Assumptions!B$25 | C8: =Assumptions!C$25 | D8: =Assumptions!D$25 | E8: =Assumptions!E$25 | F8: =Assumptions!F$25
A9: Share repurchases | B9: =B4*B8 | C9: =C4*C8 | D9: =D4*D8 | E9: =E4*E8 | F9: =F4*F8
A10: Total distributable cash flow | B10: =B7+B9 | C10: =C7+C9 | D10: =D7+D9 | E10: =E7+E9 | F10: =F7+F9
A11: Discount factor | B11: =1/(1+Assumptions!$B$9)^1 | C11: =1/(1+Assumptions!$B$9)^2 | D11: =1/(1+Assumptions!$B$9)^3 | E11: =1/(1+Assumptions!$B$9)^4 | F11: =1/(1+Assumptions!$B$9)^5
A12: Present value of distrib. CF | B12: =B10*B11 | C12: =C10*C11 | D12: =D10*D11 | E12: =E10*E11 | F12: =F10*F11
A14: Sum of PV of distributable CF | B14: =SUM(B12:F12)
A15: Terminal value (Gordon on 2030 distrib. CF) | B15: =F10*(1+Assumptions!$B$29)/(Assumptions!$B$9-Assumptions!$B$29)
A16: PV of terminal value | B16: =B15/(1+Assumptions!$B$9)^5
A17: Equity value | B17: =B14+B16
A18: Shares outstanding (M) | B18: =Assumptions!$B$32
A19: Implied value per share ($) | B19: =B17/B18

Sheet Comps
A1: Comparable companies — diversified financials
A2: Market data as of 2026-10-16 (Yahoo Finance Oct 16 closes). $ millions, except price and per-share.
B3: JPM | C3: GS | D3: MS | E3: BLK
A4: Price, Oct 16 close ($) | B4: 339.72 | C4: 881.26 | D4: 180.57 | E4: 1134.38
A5: Market cap, Oct 16 ($M) | B5: 902180.4 | C5: 256597.5 | D5: 283598.1 | E5: 175681.4
A6: Trailing EPS ($) | B6: 23.84 | C6: 69.55 | D6: 12.61 | E6: 43.92
A7: Forward EPS ($) | B7: 25.50124 | C7: 73.35655 | D7: 13.64362 | E7: 65.07481
A8: Trailing P/E | B8: =B4/B6 | C8: =C4/C6 | D8: =D4/D6 | E8: =E4/E6
A9: Forward P/E | B9: =B4/B7 | C9: =C4/C7 | D9: =D4/D7 | E9: =E4/E7
A10: Book value per share ($) | B10: 132.297 | C10: 372.246 | D10: 67.801 | E10: 371.704
A11: P / B | B11: =B4/B10 | C11: =C4/C10 | D11: =D4/D10 | E11: =E4/E10
A13: JPM implied valuation from peer multiples
A14: Median peer forward P/E | B14: =MEDIAN(C9:E9)
A15: Implied per share — forward P/E ($) | B15: =B14*B7
A17: Median peer P / B | B17: =MEDIAN(C11:E11)
A18: Implied per share — P / B ($) | B18: =B17*B10 | C18: P/B is the operative multiple for banks: book value is the clean measure of deployable capital; earnings are flattered by the 5.1% rate regime.

Sheet Checks
A1: Verification appendix
A2: Tie-outs and data provenance. Every [DATA] input is sourced; every [JUDGMENT] input carries a rationale on Assumptions.
A3: Check | B3: Detail | C3: Status
A4: Net income ties across statements | B4: Income-statement Net Income = cash-flow Net Income From Continuing Operations for FY2022-2025 (max diff $0.0M) | C4: PASS
A5: Distribution bridge | B5: FY2025: |Cash Dividends Paid| $16,625.0M + |Repurchase Of Capital Stock| $34,591.0M − Preferred Stock Dividends $1,099.0M = $50,117.0M total distributions to common (90.0% of net income common) | C5: PASS
A6: Historicals distribution formula | B6: Formula check: Total distributions = dividends + buybacks − preferred | C6: =IF(ABS(Historicals!E10-(Historicals!E8+Historicals!E9-Historicals!E7))<0.5,"PASS","FAIL")
A7: Per-share arithmetic | B7: Formula check: per-share = equity value / shares | C7: =IF(ABS(DCF_Base!B19-DCF_Base!B17/DCF_Base!B18)<0.01,"PASS","FAIL")
A8: Equity = PV sum + PV of TV | B8: Formula check | C8: =IF(ABS(DCF_Base!B17-(DCF_Base!B14+DCF_Base!B16))<0.5,"PASS","FAIL")
A9: Cost of equity arithmetic | B9: Formula check: CoE = 5.1% + beta × 4.5% | C9: =IF(ABS(Assumptions!B7-(0.051+Assumptions!B6*0.045))<0.0005,"PASS","FAIL")
A10: Terminal value arithmetic | B10: Formula check: TV = 2030 distrib × (1+g)/(CoE−g), base case | C10: =IF(ABS(DCF_Base!B15-DCF_Base!F10*(1+Assumptions!B27)/(Assumptions!B7-Assumptions!B27))<1,"PASS","FAIL")
A11: Price as-of | B11: Oct 16, 2026 close pinned from Yahoo Finance daily history (2026-10-13–20 pull); info.currentPrice is the live Oct 19 quote and is NOT used | C11: PASS
A12: Beta cross-checked | B12: Yahoo Finance 1.015 (2026-10-19); Finnhub 1.04; alcapitaladvisory 1.01; MarketBeat 1.02. Used 1.02 | C12: PASS
A13: Risk-free rate | B13: US 10Y 5.085% on 2026-10-19 (Reuters); Gate Ventures/Al Jazeera recaps ~5.09%; used 5.1% | C13: PASS
A14: MS FY2021 column blank in source | B14: Yahoo Finance annual pull carries a blank 2021 column for MS only; model uses FY2022–2025 for all four | C14: PASS
A15: DCF vs market gap is explainable | B15: Base per-share $313.42 trails $339.72 by 7.7%: the market prices slightly richer perpetual growth than my 3.0% terminal; peer forward P/E median (13.2x) implies $337 and peer P/B median (2.66x) implies $352 — both within reach of the quote, consistent with HOLD. | C15: PASS

Sheet Sources
A1: Sources
A2: Full URLs and access dates for every external input.
A3: # | B3: Source | C3: URL | D3: Accessed | E3: Used for
A4: 1 | B4: Yahoo Finance — JPM quote & financials | C4: https://finance.yahoo.com/quote/JPM | D4: 2026-10-19 | E4: Price, beta, shares, annual statements
A5: 2 | B5: Yahoo Finance — GS quote & financials | C5: https://finance.yahoo.com/quote/GS | D5: 2026-10-19 | E5: Price, beta, shares, annual statements
A6: 3 | B6: Yahoo Finance — MS quote & financials | C6: https://finance.yahoo.com/quote/MS | D6: 2026-10-19 | E6: Price, beta, shares, annual statements
A7: 4 | B7: Yahoo Finance — BLK quote & financials | C7: https://finance.yahoo.com/quote/BLK | D7: 2026-10-19 | E7: Price, beta, shares, annual statements
A8: 5 | B8: Reuters — 10Y yield 5.085% on Oct 19, 2026 | C8: https://www.reuters.com/business/wall-st-futures-climb-ai-stocks-rebound-oil-yields-fall-2026-10-19/ | D8: 2026-10-19 | E8: Risk-free rate
A9: 6 | B9: Finnhub — JPM beta | C9: https://finnhub.io/?q=%22JPM%22 | D9: 2026-10-19 | E9: Beta cross-check (1.04)
A10: 7 | B10: Finnhub — MS beta | C10: https://finnhub.io/?q=%22MS%22 | D10: 2026-10-19 | E10: Beta cross-check (1.23)
A11: 8 | B11: MarketBeat — GS | C11: https://www.marketbeat.com/stocks/NYSE/GS/ | D11: 2026-10-19 | E11: Beta cross-check (1.29)
A12: 9 | B12: MarketBeat — MS | C12: https://www.marketbeat.com/stocks/NYSE/MS/ | D12: 2026-10-19 | E12: Beta cross-check (1.22)
A13: 10 | B13: MarketBeat — BLK | C13: https://www.marketbeat.com/stocks/NYSE/BLK/ | D13: 2026-10-19 | E13: Beta cross-check (1.41, outlier vs cluster)
A14: 11 | B14: wallstreetnumbers — BLK beta history | C14: https://wallstreetnumbers.com/stocks/blk/beta | D14: 2026-10-19 | E14: Beta cross-check (1.20 on Oct 16, 2026)
A15: 12 | B15: TipRanks — BLK statistics | C15: https://www.tipranks.com/stocks/blk/statistics | D15: 2026-10-19 | E15: Beta cross-check (1.19); payout/net-cash context
A16: 13 | B16: Defense World — JPM dividend increase | C16: https://www.defenseworld.net/2026/10/18/jpmorgan-chase-co-jpm-stock-sold-by-cornerstone-enterprises-llc.html | D16: 2026-10-19 | E16: JPM quarterly dividend raised to $1.65 ($6.60 annualized)
