Workbook

Sheet Cover
A1: Equity Research Teardown — Apple Inc. (NASDAQ: AAPL)
A2: Consumer Tech sector teardown | Independent equity research project by Archit Chawla | As of October 19, 2026
A4: Current price (Oct 16, 2026 close) | B4: 343.46
A5: Recommendation | B5: PASS
A6: One-line thesis | B6: The world’s best consumer franchise at a price that assumes AI-era growth on a flat-FCF base: free cash flow was $111B in FY2022 and $99B in FY2025 while the quote implies ~7.3% perpetual growth. My DCF sits 57% below $343.46.
A8: Contents
A9: Assumptions | B9: WACC build and all forecast drivers; [DATA] vs [JUDGMENT] tags
A10: Historicals | B10: FY2022–FY2025 (fiscal years ended September 30) financials from Yahoo Finance annual statements
A11: DCF_Base / DCF_Bull / DCF_Bear | B11: 5-year DCF per case; all formulas live
A12: Comps | B12: AAPL, AMZN, META, GOOGL multiples on Oct 16, 2026 prices and implied ranges
A13: Checks | B13: Verification appendix: tie-outs and data sources
A14: Sources | B14: Full URLs and access dates
A16: Disclaimer: Independent project for skill demonstration; not investment advice.

Sheet Assumptions
A1: Assumptions
A2: Blue cells are inputs. [DATA] = market/filing data; [JUDGMENT] = analyst estimate with rationale.
A3: WACC build
A4: Risk-free rate (US 10Y) | B4: 0.051 | C4: [DATA] | D4: 5.09% on 2026-10-19 (Reuters); rounded to 5.1% (shared framework)
A5: Equity risk premium | B5: 0.045 | C5: [JUDGMENT] | D5: Long-run US ERP assumption (shared framework)
A6: Beta (AAPL) | B6: 1.07 | C6: [DATA] | D6: Yahoo Finance 2026-10-19 (1.069); cross-checked 1.07 (stockanalysis.com) and 1.07 (MarketBeat)
A7: Cost of equity (CAPM) | B7: =Assumptions!$B$4+Assumptions!$B$6*Assumptions!$B$5 | C7: [CALC] | D7: Rf + beta × ERP
A8: Pre-tax cost of debt | B8: 0.055 | C8: [JUDGMENT] | D8: Through-cycle new-issue estimate for AA+ credit in a 5.1% Treasury world (shared framework: uniform 5.5%)
A9: Marginal tax rate | B9: 0.21 | C9: [JUDGMENT] | D9: US statutory 21% (shared framework)
A10: After-tax cost of debt | B10: =Assumptions!$B$8*(1-Assumptions!$B$9) | C10: [CALC]
A11: Market value of equity ($M) | B11: 5012536 | C11: [DATA] | D11: Oct 16, 2026 close $343.46 x 14,594.2M shares (Yahoo Finance, 2026-10-19)
A12: Book value of debt ($M) | B12: 84344 | C12: [DATA] | D12: Q3 FY2026 balance sheet, Jun 2026 (Yahoo Finance)
A13: Weight of equity | B13: =Assumptions!$B$11/(Assumptions!$B$11+Assumptions!$B$12) | C13: [CALC]
A14: Weight of debt | B14: =Assumptions!$B$12/(Assumptions!$B$11+Assumptions!$B$12) | C14: [CALC]
A15: WACC — base case | B15: =Assumptions!$B$13*Assumptions!$B$7+Assumptions!$B$14*Assumptions!$B$10 | C15: [CALC]
A16: WACC — bull case (-100 bps) | B16: =Assumptions!$B$15-0.01 | C16: [CALC] | D16: Rate-normalization scenario (shared framework)
A17: WACC — bear case (+100 bps) | B17: =Assumptions!$B$15+0.01 | C17: [CALC] | D17: Higher-for-longer scenario (shared framework)
A19: Forecast drivers (2026–2030)
B20: 2026 | C20: 2027 | D20: 2028 | E20: 2029 | F20: 2030
A21: Revenue growth — base | B21: 0.1 | C21: 0.08 | D21: 0.06 | E21: 0.05 | F21: 0.04 | G21: [JUDGMENT] | H21: FY2026E +10% (Dec-quarter guide 10–12%; Q3 FY2026 rev +16.4% YoY), tapering to 4% as the iPhone cycle matures
A22: Revenue growth — bull | B22: 0.14 | C22: 0.11 | D22: 0.09 | E22: 0.07 | F22: 0.06 | G22: [JUDGMENT] | H22: AI-feature iPhone supercycle + services acceleration
A23: Revenue growth — bear | B23: 0.05 | C23: 0.03 | D23: 0.02 | E23: 0.01 | F23: 0 | G23: [JUDGMENT] | H23: China share loss continues; upgrade cycle extends; App Store take-rate hit
A24: EBITDA margin — base | B24: 0.355 | C24: 0.36 | D24: 0.365 | E24: 0.37 | F24: 0.375 | G24: [JUDGMENT] | H24: FY2025: 34.8%; services mix (75.4% gross margin vs 36.8% products) lifts blended margin ~50 bps/yr
A25: EBITDA margin — bull | B25: 0.37 | C25: 0.375 | D25: 0.38 | E25: 0.385 | F25: 0.39 | G25: [JUDGMENT] | H25: Faster services mix shift; Pro-model pricing power
A26: EBITDA margin — bear | B26: 0.33 | C26: 0.325 | D26: 0.32 | E26: 0.315 | F26: 0.31 | G26: [JUDGMENT] | H26: App Store commission pressure (US court order, EU DMA); China promo
A28: D&A (% of revenue) | B28: 0.028 | G28: [JUDGMENT] | H28: FY2025: 2.8% of revenue (11,698 / 416,161)
A29: Stock-based comp. (% of revenue) | B29: 0.031 | C29: 0.03 | D29: 0.029 | E29: 0.028 | F29: 0.027 | G29: [JUDGMENT] | H29: FY2025: 3.1% of revenue (12,863 / 416,161); easing with scale
A30: Capex (% of revenue) | B30: 0.032 | G30: [JUDGMENT] | H30: FY2025: 3.1% (12,715 / 416,161); AI/data-center build adds ~10 bps
A31: Change in NWC (% of revenue growth) | B31: 0.04 | G31: [JUDGMENT] | H31: Uniform working-capital intensity (shared framework)
A32: Terminal growth — base | B32: 0.03 | G32: [JUDGMENT] | H32: Long-run nominal GDP (shared framework)
A33: Terminal growth — bull | B33: 0.035 | G33: [JUDGMENT] | H33: Shared framework
A34: Terminal growth — bear | B34: 0.02 | G34: [JUDGMENT] | H34: Shared framework
A35: Net debt ($M) | B35: 21945 | G35: [DATA] | H35: Q3 FY2026: total debt 84,344 less cash 39,544 and ST investments 22,855
A36: Shares outstanding (M) | B36: 14594.18 | G36: [DATA] | H36: Yahoo Finance 2026-10-19 (14,594.2M); stockanalysis.com 14.59B — consistent with market cap / price

Sheet Historicals
A1: Historical financials — AAPL
A2: $ millions. FY2022–FY2025 (fiscal years ended September 30). Source: Yahoo Finance annual statements (filing-derived), as of 2026-10-19.
B3: 2022 | C3: 2023 | D3: 2024 | E3: 2025
A4: Total revenue | B4: 394328 | C4: 383285 | D4: 391035 | E4: 416161
A5: Gross profit | B5: 170782 | C5: 169148 | D5: 180683 | E5: 195201
A6: EBITDA | B6: 130541 | C6: 125820 | D6: 134661 | E6: 144748
A7: EBITDA margin | B7: =B6/B4 | C7: =C6/C4 | D7: =D6/D4 | E7: =E6/E4
A8: Operating income | B8: 119437 | C8: 114301 | D8: 123216 | E8: 133050
A9: Net income | B9: 99803 | C9: 96995 | D9: 93736 | E9: 112010
A10: Diluted average shares (M) | B10: 16325.8 | C10: 15812.5 | D10: 15408.1 | E10: 15004.7
A11: Operating cash flow | B11: 122151 | C11: 110543 | D11: 118254 | E11: 111482
A12: Capital expenditures | B12: -10708 | C12: -10959 | D12: -9447 | E12: -12715
A13: Free cash flow | B13: 111443 | C13: 99584 | D13: 108807 | E13: 98767
A14: Cash & ST investments | B14: 48304 | C14: 61555 | D14: 65171 | E14: 54697
A15: Total debt | B15: 132480 | C15: 111088 | D15: 106629 | E15: 98657
A16: Revenue growth | C16: =C4/B4-1 | D16: =D4/C4-1 | E16: =E4/D4-1

Sheet DCF_Base
A1: Apple Inc. (AAPL) — Discounted cash flow — base case
A2: $ millions, except per-share. All formulas reference Assumptions / Historicals.
B3: 2026 | C3: 2027 | D3: 2028 | E3: 2029 | F3: 2030
A4: Revenue | B4: =Historicals!$E$4*(1+Assumptions!B$21) | C4: =B4*(1+Assumptions!C$21) | D4: =C4*(1+Assumptions!D$21) | E4: =D4*(1+Assumptions!E$21) | F4: =E4*(1+Assumptions!F$21)
A5: Revenue growth | B5: =B4/Historicals!$E$4-1 | C5: =C4/B4-1 | D5: =D4/C4-1 | E5: =E4/D4-1 | F5: =F4/E4-1
A6: EBITDA margin | B6: =Assumptions!B$24 | C6: =Assumptions!C$24 | D6: =Assumptions!D$24 | E6: =Assumptions!E$24 | F6: =Assumptions!F$24
A7: EBITDA | B7: =B4*B6 | C7: =C4*C6 | D7: =D4*D6 | E7: =E4*E6 | F7: =F4*F6
A8: Less: Depreciation & amortization | B8: =B4*Assumptions!$B$28 | C8: =C4*Assumptions!$B$28 | D8: =D4*Assumptions!$B$28 | E8: =E4*Assumptions!$B$28 | F8: =F4*Assumptions!$B$28
A9: EBIT | B9: =B7-B8 | C9: =C7-C8 | D9: =D7-D8 | E9: =E7-E8 | F9: =F7-F8
A10: Tax rate | B10: =Assumptions!$B$9 | C10: =Assumptions!$B$9 | D10: =Assumptions!$B$9 | E10: =Assumptions!$B$9 | F10: =Assumptions!$B$9
A11: Less: Income tax | B11: =B9*B10 | C11: =C9*C10 | D11: =D9*D10 | E11: =E9*E10 | F11: =F9*F10
A12: NOPAT | B12: =B9-B11 | C12: =C9-C11 | D12: =D9-D11 | E12: =E9-E11 | F12: =F9-F11
A13: Add: Stock-based compensation | B13: =B4*Assumptions!B$29 | C13: =C4*Assumptions!C$29 | D13: =D4*Assumptions!D$29 | E13: =E4*Assumptions!E$29 | F13: =F4*Assumptions!F$29
A14: Less: Capital expenditures | B14: =B4*Assumptions!$B$30 | C14: =C4*Assumptions!$B$30 | D14: =D4*Assumptions!$B$30 | E14: =E4*Assumptions!$B$30 | F14: =F4*Assumptions!$B$30
A15: Less: Change in net working capital | B15: =(B4-Historicals!$E$4)*Assumptions!$B$31 | C15: =(C4-B4)*Assumptions!$B$31 | D15: =(D4-C4)*Assumptions!$B$31 | E15: =(E4-D4)*Assumptions!$B$31 | F15: =(F4-E4)*Assumptions!$B$31
A16: Unlevered free cash flow | B16: =B12+B8+B13-B14-B15 | C16: =C12+C8+C13-C14-C15 | D16: =D12+D8+D13-D14-D15 | E16: =E12+E8+E13-E14-E15 | F16: =F12+F8+F13-F14-F15
A17: Discount factor | B17: =1/(1+Assumptions!$B$15)^1 | C17: =1/(1+Assumptions!$B$15)^2 | D17: =1/(1+Assumptions!$B$15)^3 | E17: =1/(1+Assumptions!$B$15)^4 | F17: =1/(1+Assumptions!$B$15)^5
A18: Present value of FCF | B18: =B16*B17 | C18: =C16*C17 | D18: =D16*D17 | E18: =E16*E17 | F18: =F16*F17
A19: Sum of PV of FCF | B19: =SUM(B18:F18)
A20: Terminal value | B20: =F16*(1+Assumptions!$B$32)/(Assumptions!$B$15-Assumptions!$B$32)
A21: PV of terminal value | B21: =B20/(1+Assumptions!$B$15)^5
A22: Enterprise value | B22: =B19+B21
A23: Less: Net debt (add: net cash) | B23: =Assumptions!$B$35
A24: Equity value | B24: =B22-B23
A25: Shares outstanding (M) | B25: =Assumptions!$B$36
A26: Implied value per share ($) | B26: =B24/B25

Sheet DCF_Bull
A1: Apple Inc. (AAPL) — Discounted cash flow — bull case
A2: $ millions, except per-share. All formulas reference Assumptions / Historicals.
B3: 2026 | C3: 2027 | D3: 2028 | E3: 2029 | F3: 2030
A4: Revenue | B4: =Historicals!$E$4*(1+Assumptions!B$22) | C4: =B4*(1+Assumptions!C$22) | D4: =C4*(1+Assumptions!D$22) | E4: =D4*(1+Assumptions!E$22) | F4: =E4*(1+Assumptions!F$22)
A5: Revenue growth | B5: =B4/Historicals!$E$4-1 | C5: =C4/B4-1 | D5: =D4/C4-1 | E5: =E4/D4-1 | F5: =F4/E4-1
A6: EBITDA margin | B6: =Assumptions!B$25 | C6: =Assumptions!C$25 | D6: =Assumptions!D$25 | E6: =Assumptions!E$25 | F6: =Assumptions!F$25
A7: EBITDA | B7: =B4*B6 | C7: =C4*C6 | D7: =D4*D6 | E7: =E4*E6 | F7: =F4*F6
A8: Less: Depreciation & amortization | B8: =B4*Assumptions!$B$28 | C8: =C4*Assumptions!$B$28 | D8: =D4*Assumptions!$B$28 | E8: =E4*Assumptions!$B$28 | F8: =F4*Assumptions!$B$28
A9: EBIT | B9: =B7-B8 | C9: =C7-C8 | D9: =D7-D8 | E9: =E7-E8 | F9: =F7-F8
A10: Tax rate | B10: =Assumptions!$B$9 | C10: =Assumptions!$B$9 | D10: =Assumptions!$B$9 | E10: =Assumptions!$B$9 | F10: =Assumptions!$B$9
A11: Less: Income tax | B11: =B9*B10 | C11: =C9*C10 | D11: =D9*D10 | E11: =E9*E10 | F11: =F9*F10
A12: NOPAT | B12: =B9-B11 | C12: =C9-C11 | D12: =D9-D11 | E12: =E9-E11 | F12: =F9-F11
A13: Add: Stock-based compensation | B13: =B4*Assumptions!B$29 | C13: =C4*Assumptions!C$29 | D13: =D4*Assumptions!D$29 | E13: =E4*Assumptions!E$29 | F13: =F4*Assumptions!F$29
A14: Less: Capital expenditures | B14: =B4*Assumptions!$B$30 | C14: =C4*Assumptions!$B$30 | D14: =D4*Assumptions!$B$30 | E14: =E4*Assumptions!$B$30 | F14: =F4*Assumptions!$B$30
A15: Less: Change in net working capital | B15: =(B4-Historicals!$E$4)*Assumptions!$B$31 | C15: =(C4-B4)*Assumptions!$B$31 | D15: =(D4-C4)*Assumptions!$B$31 | E15: =(E4-D4)*Assumptions!$B$31 | F15: =(F4-E4)*Assumptions!$B$31
A16: Unlevered free cash flow | B16: =B12+B8+B13-B14-B15 | C16: =C12+C8+C13-C14-C15 | D16: =D12+D8+D13-D14-D15 | E16: =E12+E8+E13-E14-E15 | F16: =F12+F8+F13-F14-F15
A17: Discount factor | B17: =1/(1+Assumptions!$B$16)^1 | C17: =1/(1+Assumptions!$B$16)^2 | D17: =1/(1+Assumptions!$B$16)^3 | E17: =1/(1+Assumptions!$B$16)^4 | F17: =1/(1+Assumptions!$B$16)^5
A18: Present value of FCF | B18: =B16*B17 | C18: =C16*C17 | D18: =D16*D17 | E18: =E16*E17 | F18: =F16*F17
A19: Sum of PV of FCF | B19: =SUM(B18:F18)
A20: Terminal value | B20: =F16*(1+Assumptions!$B$33)/(Assumptions!$B$16-Assumptions!$B$33)
A21: PV of terminal value | B21: =B20/(1+Assumptions!$B$16)^5
A22: Enterprise value | B22: =B19+B21
A23: Less: Net debt (add: net cash) | B23: =Assumptions!$B$35
A24: Equity value | B24: =B22-B23
A25: Shares outstanding (M) | B25: =Assumptions!$B$36
A26: Implied value per share ($) | B26: =B24/B25

Sheet DCF_Bear
A1: Apple Inc. (AAPL) — Discounted cash flow — bear case
A2: $ millions, except per-share. All formulas reference Assumptions / Historicals.
B3: 2026 | C3: 2027 | D3: 2028 | E3: 2029 | F3: 2030
A4: Revenue | B4: =Historicals!$E$4*(1+Assumptions!B$23) | C4: =B4*(1+Assumptions!C$23) | D4: =C4*(1+Assumptions!D$23) | E4: =D4*(1+Assumptions!E$23) | F4: =E4*(1+Assumptions!F$23)
A5: Revenue growth | B5: =B4/Historicals!$E$4-1 | C5: =C4/B4-1 | D5: =D4/C4-1 | E5: =E4/D4-1 | F5: =F4/E4-1
A6: EBITDA margin | B6: =Assumptions!B$26 | C6: =Assumptions!C$26 | D6: =Assumptions!D$26 | E6: =Assumptions!E$26 | F6: =Assumptions!F$26
A7: EBITDA | B7: =B4*B6 | C7: =C4*C6 | D7: =D4*D6 | E7: =E4*E6 | F7: =F4*F6
A8: Less: Depreciation & amortization | B8: =B4*Assumptions!$B$28 | C8: =C4*Assumptions!$B$28 | D8: =D4*Assumptions!$B$28 | E8: =E4*Assumptions!$B$28 | F8: =F4*Assumptions!$B$28
A9: EBIT | B9: =B7-B8 | C9: =C7-C8 | D9: =D7-D8 | E9: =E7-E8 | F9: =F7-F8
A10: Tax rate | B10: =Assumptions!$B$9 | C10: =Assumptions!$B$9 | D10: =Assumptions!$B$9 | E10: =Assumptions!$B$9 | F10: =Assumptions!$B$9
A11: Less: Income tax | B11: =B9*B10 | C11: =C9*C10 | D11: =D9*D10 | E11: =E9*E10 | F11: =F9*F10
A12: NOPAT | B12: =B9-B11 | C12: =C9-C11 | D12: =D9-D11 | E12: =E9-E11 | F12: =F9-F11
A13: Add: Stock-based compensation | B13: =B4*Assumptions!B$29 | C13: =C4*Assumptions!C$29 | D13: =D4*Assumptions!D$29 | E13: =E4*Assumptions!E$29 | F13: =F4*Assumptions!F$29
A14: Less: Capital expenditures | B14: =B4*Assumptions!$B$30 | C14: =C4*Assumptions!$B$30 | D14: =D4*Assumptions!$B$30 | E14: =E4*Assumptions!$B$30 | F14: =F4*Assumptions!$B$30
A15: Less: Change in net working capital | B15: =(B4-Historicals!$E$4)*Assumptions!$B$31 | C15: =(C4-B4)*Assumptions!$B$31 | D15: =(D4-C4)*Assumptions!$B$31 | E15: =(E4-D4)*Assumptions!$B$31 | F15: =(F4-E4)*Assumptions!$B$31
A16: Unlevered free cash flow | B16: =B12+B8+B13-B14-B15 | C16: =C12+C8+C13-C14-C15 | D16: =D12+D8+D13-D14-D15 | E16: =E12+E8+E13-E14-E15 | F16: =F12+F8+F13-F14-F15
A17: Discount factor | B17: =1/(1+Assumptions!$B$17)^1 | C17: =1/(1+Assumptions!$B$17)^2 | D17: =1/(1+Assumptions!$B$17)^3 | E17: =1/(1+Assumptions!$B$17)^4 | F17: =1/(1+Assumptions!$B$17)^5
A18: Present value of FCF | B18: =B16*B17 | C18: =C16*C17 | D18: =D16*D17 | E18: =E16*E17 | F18: =F16*F17
A19: Sum of PV of FCF | B19: =SUM(B18:F18)
A20: Terminal value | B20: =F16*(1+Assumptions!$B$34)/(Assumptions!$B$17-Assumptions!$B$34)
A21: PV of terminal value | B21: =B20/(1+Assumptions!$B$17)^5
A22: Enterprise value | B22: =B19+B21
A23: Less: Net debt (add: net cash) | B23: =Assumptions!$B$35
A24: Equity value | B24: =B22-B23
A25: Shares outstanding (M) | B25: =Assumptions!$B$36
A26: Implied value per share ($) | B26: =B24/B25

Sheet Comps
A1: Comparable companies — AAPL vs Consumer Tech peers
A2: Market data as of Oct 16, 2026 closes (Yahoo Finance). $ millions, except price and per-share.
B3: AAPL | C3: AMZN | D3: META | E3: GOOGL
A4: Price ($) | B4: 343.46 | C4: 250 | D4: 709.33 | E4: 340.59
A5: Market cap ($M) | B5: 5012536 | C5: 2696578 | D5: 1808792 | E5: 4165416
A6: Enterprise value ($M) | B6: 5034481 | C6: 2763377 | D6: 1830850 | E6: 4035698
A7: Revenue, TTM ($M) | B7: 466823 | C7: 775680 | D7: 228247 | E7: 445866
A8: EBITDA, TTM ($M) | B8: 167959 | C8: 168912 | D8: 109655 | E8: 173164
A9: Trailing EPS ($) | B9: 8.72 | C9: 12.43 | D9: 26.54 | E9: 19.93
A10: Forward EPS ($) | B10: 9.57785 | C10: 10.44315 | D10: 34.62667 | E10: 15.29162
A11: EV / Revenue | B11: =B6/B7 | C11: =C6/C7 | D11: =D6/D7 | E11: =E6/E7
A12: EV / EBITDA | B12: =B6/B8 | C12: =C6/C8 | D12: =D6/D8 | E12: =E6/E8
A13: Trailing P/E | B13: =B4/B9 | C13: =C4/C9 | D13: =D4/D9 | E13: =E4/E9
A14: Forward P/E | B14: =B4/B10 | C14: =C4/C10 | D14: =D4/D10 | E14: =E4/E10
A16: AAPL implied valuation from peer medians
A17: Median peer EV / Revenue | B17: =MEDIAN(C11:E11)
A18: Implied EV ($M) | B18: =B17*B7
A19: Less: Net debt ($M) | B19: =Assumptions!$B$35
A20: Implied per share — EV/Revenue ($) | B20: =(B18-B19)/Assumptions!$B$36
A22: Median peer EV / EBITDA | B22: =MEDIAN(C12:E12)
A23: Implied EV ($M) | B23: =B22*B8
A24: Implied per share — EV/EBITDA ($) | B24: =(B23-Assumptions!$B$35)/Assumptions!$B$36
A26: Median peer forward P/E | B26: =MEDIAN(C14:E14)
A27: AAPL forward EPS ($) | B27: =B10
A28: Implied per share — forward P/E ($) | B28: =B26*B27 | C28: Forward P/E is the operative lens: EV multiples blend hardware, ads, and cloud mixes.

Sheet Checks
A1: Verification appendix
A2: Tie-outs and data provenance. Every [DATA] input is sourced; every [JUDGMENT] input carries a rationale on Assumptions.
A3: Check | B3: Detail | C3: Status
A4: Net income ties across statements | B4: Income-statement net income = cash-flow starting net income for FY2022–2025 (max diff $0.0M) | C4: PASS
A5: Revenue sourced from filings | B5: FY2022–2025 total revenue 394,328 / 383,285 / 391,035 / 416,161 ($M), fiscal years ended September (Yahoo Finance annual income statement) | C5: PASS
A6: Share count | B6: 14,594.2M outstanding (Yahoo Finance, Oct 2026); stockanalysis.com 14.59B; market cap ÷ price implies 14.58B — all consistent | C6: PASS
A7: Net debt bridge | B7: Q3 FY2026 balance sheet (Jun 2026): total debt $84,344M less cash $39,544M and ST investments $22,855M = net debt $21,945M | C7: PASS
A8: Beta | B8: 1.07 (Yahoo Finance 1.069, 2026-10-19); cross-checked 1.07 (stockanalysis.com) and 1.07 (MarketBeat) | C8: PASS
A9: Risk-free rate | B9: US 10Y 5.085% on 2026-10-19 (Reuters); used 5.1% (shared framework) | C9: PASS
A10: Comps market data as-of | B10: AAPL / AMZN / META / GOOGL Oct 16, 2026 closes from Yahoo Finance 1-mo history; EVs = Oct-16 market cap + latest-quarter net debt | C10: PASS
A11: FCF bridge reconciles | B11: Formula check: EV = sum of PV of FCF + PV of terminal value | C11: =IF(ABS(DCF_Base!B22-(DCF_Base!B19+DCF_Base!B21))<0.5,"PASS","FAIL")
A12: Per-share arithmetic | B12: Formula check: per-share = equity value / shares | C12: =IF(ABS(DCF_Base!B26-DCF_Base!B24/DCF_Base!B25)<0.01,"PASS","FAIL")
A13: DCF vs market gap is explainable | B13: Base per-share trails $343.46 because the quote implies ~7.3% perpetual FCF growth (my arithmetic); FCF was $111B in FY2022 and $99B in FY2025 — the market prices a growth step-change the cash flows have not shown | C13: PASS
A14: Fiscal year-ends in September | B14: Yahoo annual columns are fiscal years ended Sep 30; FY2026 (ended Sep 2026) not yet filed as of Oct 19 — forecast starts from FY2025 actuals; Q4 FY2026 earnings due Nov 2, 2026 | C14: PASS

Sheet Sources
A1: Sources
A2: Full URLs and access dates for every external input.
A3: # | B3: Source | C3: URL | D3: Accessed | E3: Used for
A4: 1 | B4: Yahoo Finance — AAPL quote & financials | C4: https://finance.yahoo.com/quote/AAPL | D4: 2026-10-19 | E4: Price, beta, shares, annual/quarterly statements, Oct-16 close
A5: 2 | B5: Yahoo Finance — AMZN | C5: https://finance.yahoo.com/quote/AMZN | D5: 2026-10-19 | E5: Comps market data
A6: 3 | B6: Yahoo Finance — META | C6: https://finance.yahoo.com/quote/META | D6: 2026-10-19 | E6: Comps market data
A7: 4 | B7: Yahoo Finance — GOOGL | C7: https://finance.yahoo.com/quote/GOOGL | D7: 2026-10-19 | E7: Comps market data
A8: 5 | B8: Reuters — 10Y yield 5.085% on Oct 19, 2026 | C8: https://www.reuters.com/business/wall-st-futures-climb-ai-stocks-rebound-oil-yields-fall-2026-10-19/ | D8: 2026-10-19 | E8: Risk-free rate
A9: 6 | B9: stockanalysis.com — AAPL overview | C9: https://stockanalysis.com/stocks/aapl/ | D9: 2026-10-19 | E9: Beta (1.07), shares outstanding (14.59B), Oct-16 price cross-check
A10: 7 | B10: fourweekmba — Apple revenue model (Oct 2026) | C10: https://fourweekmba.com/apple-business-model/ | D10: 2026-10-19 | E10: FY2025 category split: iPhone $209.6B, Services $109.2B at 75.4% gross margin
A11: 8 | B11: SQ Magazine — Apple sales statistics | C11: https://sqmagazine.co.uk/apple-sales-statistics/ | D11: 2026-10-19 | E11: FY2025 category table; Q1 FY2026 $143.8B quarter; Dec-quarter guide 10–12%
