Workbook

Sheet Cover
A1: Equity Research Teardown — Robinhood Markets, Inc. (NASDAQ: HOOD)
A2: Independent equity research project by Archit Chawla | As of October 19, 2026
A4: Current price (Oct 16, 2026 close) | B4: 98.87
A5: Recommendation | B5: PASS
A6: One-line thesis | B6: Exceptional, founder-led brokerage priced for perfection: even the bull case sits ~50% below the market price in a 5.1% rate world.
A8: Contents
A9: Assumptions | B9: WACC build and all forecast drivers; [DATA] vs [JUDGMENT] tags
A10: Historicals | B10: FY2022–2025 financials from Yahoo Finance annual statements
A11: DCF_Base / DCF_Bull / DCF_Bear | B11: 5-year DCF per case; all formulas live
A12: Comps | B12: COIN, SOFI, SCHW, IBKR multiples and HOOD-implied ranges
A13: Sensitivity | B13: Base-case per-share value vs WACC and terminal growth
A14: Checks | B14: Verification appendix: tie-outs and data sources
A15: Sources | B15: Full URLs and access dates
A17: Disclaimer: Independent project for skill demonstration; not investment advice.

Sheet Assumptions
A1: Assumptions
A2: Blue cells are inputs. [DATA] = market/filing data; [JUDGMENT] = analyst estimate with rationale.
A3: WACC build
A4: Risk-free rate (US 10Y) | B4: 0.051 | C4: [DATA] | D4: 5.09% on 2026-10-19 (Reuters); rounded to 5.1%
A5: Equity risk premium | B5: 0.045 | C5: [JUDGMENT] | D5: Long-run US ERP assumption
A6: Beta (HOOD) | B6: 2.35 | C6: [DATA] | D6: Yahoo Finance 2026-10-19; cross-checked 2.35–2.48
A7: Cost of equity (CAPM) | B7: =Assumptions!$B$4+Assumptions!$B$6*Assumptions!$B$5 | C7: [CALC] | D7: Rf + beta × ERP
A8: Pre-tax cost of debt | B8: 0.055 | C8: [JUDGMENT] | D8: Through-cycle new-issue est.; 2025 cash interest was only $31M on near-zero-coupon converts
A9: Marginal tax rate | B9: 0.21 | C9: [JUDGMENT] | D9: US statutory; 2024–25 effective rate distorted by valuation-allowance moves
A10: After-tax cost of debt | B10: =Assumptions!$B$8*(1-Assumptions!$B$9) | C10: [CALC]
A11: Market value of equity ($M) | B11: 88892.3 | C11: [DATA] | D11: Yahoo Finance 2026-10-19: $98.87 × 899.1M shares
A12: Book value of debt ($M) | B12: 22706 | C12: [DATA] | D12: Q2 2026 balance sheet (Yahoo Finance)
A13: Weight of equity | B13: =Assumptions!$B$11/(Assumptions!$B$11+Assumptions!$B$12) | C13: [CALC]
A14: Weight of debt | B14: =Assumptions!$B$12/(Assumptions!$B$11+Assumptions!$B$12) | C14: [CALC]
A15: WACC — base case | B15: =Assumptions!$B$13*Assumptions!$B$7+Assumptions!$B$14*Assumptions!$B$10 | C15: [CALC]
A16: WACC — bull case (-100 bps) | B16: =Assumptions!$B$15-0.01 | C16: [CALC] | D16: Rate-normalization scenario
A17: WACC — bear case (+100 bps) | B17: =Assumptions!$B$15+0.01 | C17: [CALC] | D17: Higher-for-longer scenario
A19: Forecast drivers (2026–2030)
B20: 2026 | C20: 2027 | D20: 2028 | E20: 2029 | F20: 2030
A21: Revenue growth — base | B21: 0.35 | C21: 0.25 | D21: 0.2 | E21: 0.17 | F21: 0.125 | G21: [JUDGMENT] | H21: Taper from 51.6% (2025); street expects ~39% for 2026 (TipRanks)
A22: Revenue growth — bull | B22: 0.4 | C22: 0.3 | D22: 0.25 | E22: 0.22 | F22: 0.175 | G22: [JUDGMENT] | H22: Sustained crypto/options supercycle
A23: Revenue growth — bear | B23: 0.27 | C23: 0.17 | D23: 0.12 | E23: 0.09 | F23: 0.045 | G23: [JUDGMENT] | H23: Rate cuts compress net interest income; trading slowdown
A24: EBITDA margin — base | B24: 0.5 | C24: 0.52 | D24: 0.54 | E24: 0.55 | F24: 0.56 | G24: [JUDGMENT] | H24: 2025: 48.7%; scale toward mature-broker margin
A25: EBITDA margin — bull | B25: 0.52 | C25: 0.54 | D25: 0.56 | E25: 0.57 | F25: 0.58 | G25: [JUDGMENT] | H25: Faster operating leverage
A26: EBITDA margin — bear | B26: 0.46 | C26: 0.48 | D26: 0.5 | E26: 0.51 | F26: 0.52 | G26: [JUDGMENT] | H26: Margin pressure from competition/promo
A28: D&A (% of revenue) | B28: 0.02 | G28: [JUDGMENT] | H28: 2025: 1.9%
A29: Stock-based comp. (% of revenue) | B29: 0.06 | C29: 0.055 | D29: 0.05 | E29: 0.045 | F29: 0.04 | G29: [JUDGMENT] | H29: 2025: 6.8%; declining with scale
A30: Capex (% of revenue) | B30: 0.012 | G30: [JUDGMENT] | H30: 2025: 1.2%
A31: Change in NWC (% of revenue growth) | B31: 0.04 | G31: [JUDGMENT] | H31: Brokerage receivables scale with activity
A32: Terminal growth — base | B32: 0.03 | G32: [JUDGMENT] | H32: Long-run nominal GDP
A33: Terminal growth — bull | B33: 0.035 | G33: [JUDGMENT]
A34: Terminal growth — bear | B34: 0.02 | G34: [JUDGMENT]
A35: Net debt ($M) | B35: 17344 | G35: [DATA] | H35: Q2 2026: total debt 22,706 less cash 5,362
A36: Diluted shares outstanding (M) | B36: 899.1 | G36: [DATA] | H36: Yahoo Finance / stockanalysis.com, Oct 2026 (FY2025 diluted avg: 918.8M)

Sheet Historicals
A1: Historical financials — HOOD
A2: $ millions. Source: Yahoo Finance annual statements (filing-derived), as of 2026-10-19.
B3: 2022 | C3: 2023 | D3: 2024 | E3: 2025
A4: Total revenue | B4: 1358 | C4: 1865 | D4: 2951 | E4: 4473
A5: Gross profit | B5: 770 | C5: 1719 | D5: 2344 | E5: 3728
A6: EBITDA | B6: -905 | C6: -465 | D6: 1131 | E6: 2180
A7: EBITDA margin | B7: =B6/B4 | C7: =C6/C4 | D7: =D6/D4 | E7: =E6/E4
A8: Operating income | B8: -966 | C8: -536 | D8: 1054 | E8: 2094
A9: Net income | B9: -1028 | C9: -541 | D9: 1411 | E9: 1883
A10: Diluted average shares (M) | B10: 878.6 | C10: 890.9 | D10: 906.2 | E10: 918.8
A11: Operating cash flow | B11: -852 | C11: 1181 | D11: -157 | E11: 1638
A12: Capital expenditures | B12: -57 | C12: -21 | D12: -50 | E12: -54
A13: Free cash flow | B13: -909 | C13: 1160 | D13: -207 | E13: 1584
A14: Cash & equivalents | B14: 6339 | C14: 4835 | D14: 4332 | E14: 4261
A15: Total debt | B15: 1834 | C15: 3547 | D15: 7463 | E15: 11626
A16: Revenue growth | C16: =C4/B4-1 | D16: =D4/C4-1 | E16: =E4/D4-1

Sheet DCF_Base
A1: Robinhood Markets, Inc. (HOOD) — Discounted cash flow — base case
A2: $ millions, except per-share. All formulas reference Assumptions / Historicals.
B3: 2026 | C3: 2027 | D3: 2028 | E3: 2029 | F3: 2030
A4: Revenue | B4: =Historicals!$E$4*(1+Assumptions!B$21) | C4: =B4*(1+Assumptions!C$21) | D4: =C4*(1+Assumptions!D$21) | E4: =D4*(1+Assumptions!E$21) | F4: =E4*(1+Assumptions!F$21)
A5: Revenue growth | B5: =B4/Historicals!$E$4-1 | C5: =C4/B4-1 | D5: =D4/C4-1 | E5: =E4/D4-1 | F5: =F4/E4-1
A6: EBITDA margin | B6: =Assumptions!B$24 | C6: =Assumptions!C$24 | D6: =Assumptions!D$24 | E6: =Assumptions!E$24 | F6: =Assumptions!F$24
A7: EBITDA | B7: =B4*B6 | C7: =C4*C6 | D7: =D4*D6 | E7: =E4*E6 | F7: =F4*F6
A8: Less: Depreciation & amortization | B8: =B4*Assumptions!$B$28 | C8: =C4*Assumptions!$B$28 | D8: =D4*Assumptions!$B$28 | E8: =E4*Assumptions!$B$28 | F8: =F4*Assumptions!$B$28
A9: EBIT | B9: =B7-B8 | C9: =C7-C8 | D9: =D7-D8 | E9: =E7-E8 | F9: =F7-F8
A10: Tax rate | B10: =Assumptions!$B$9 | C10: =Assumptions!$B$9 | D10: =Assumptions!$B$9 | E10: =Assumptions!$B$9 | F10: =Assumptions!$B$9
A11: Less: Income tax | B11: =B9*B10 | C11: =C9*C10 | D11: =D9*D10 | E11: =E9*E10 | F11: =F9*F10
A12: NOPAT | B12: =B9-B11 | C12: =C9-C11 | D12: =D9-D11 | E12: =E9-E11 | F12: =F9-F11
A13: Add: Stock-based compensation | B13: =B4*Assumptions!B$29 | C13: =C4*Assumptions!C$29 | D13: =D4*Assumptions!D$29 | E13: =E4*Assumptions!E$29 | F13: =F4*Assumptions!F$29
A14: Less: Capital expenditures | B14: =B4*Assumptions!$B$30 | C14: =C4*Assumptions!$B$30 | D14: =D4*Assumptions!$B$30 | E14: =E4*Assumptions!$B$30 | F14: =F4*Assumptions!$B$30
A15: Less: Change in net working capital | B15: =(B4-Historicals!$E$4)*Assumptions!$B$31 | C15: =(C4-B4)*Assumptions!$B$31 | D15: =(D4-C4)*Assumptions!$B$31 | E15: =(E4-D4)*Assumptions!$B$31 | F15: =(F4-E4)*Assumptions!$B$31
A16: Unlevered free cash flow | B16: =B12+B8+B13-B14-B15 | C16: =C12+C8+C13-C14-C15 | D16: =D12+D8+D13-D14-D15 | E16: =E12+E8+E13-E14-E15 | F16: =F12+F8+F13-F14-F15
A17: Discount factor | B17: =1/(1+Assumptions!$B$15)^1 | C17: =1/(1+Assumptions!$B$15)^2 | D17: =1/(1+Assumptions!$B$15)^3 | E17: =1/(1+Assumptions!$B$15)^4 | F17: =1/(1+Assumptions!$B$15)^5
A18: Present value of FCF | B18: =B16*B17 | C18: =C16*C17 | D18: =D16*D17 | E18: =E16*E17 | F18: =F16*F17
A19: Sum of PV of FCF | B19: =SUM(B18:F18)
A20: Terminal value | B20: =F16*(1+Assumptions!$B$32)/(Assumptions!$B$15-Assumptions!$B$32)
A21: PV of terminal value | B21: =B20/(1+Assumptions!$B$15)^5
A22: Enterprise value | B22: =B19+B21
A23: Less: Net debt | B23: =Assumptions!$B$35
A24: Equity value | B24: =B22-B23
A25: Diluted shares outstanding (M) | B25: =Assumptions!$B$36
A26: Implied value per share ($) | B26: =B24/B25

Sheet DCF_Bull
A1: Robinhood Markets, Inc. (HOOD) — Discounted cash flow — bull case
A2: $ millions, except per-share. All formulas reference Assumptions / Historicals.
B3: 2026 | C3: 2027 | D3: 2028 | E3: 2029 | F3: 2030
A4: Revenue | B4: =Historicals!$E$4*(1+Assumptions!B$22) | C4: =B4*(1+Assumptions!C$22) | D4: =C4*(1+Assumptions!D$22) | E4: =D4*(1+Assumptions!E$22) | F4: =E4*(1+Assumptions!F$22)
A5: Revenue growth | B5: =B4/Historicals!$E$4-1 | C5: =C4/B4-1 | D5: =D4/C4-1 | E5: =E4/D4-1 | F5: =F4/E4-1
A6: EBITDA margin | B6: =Assumptions!B$25 | C6: =Assumptions!C$25 | D6: =Assumptions!D$25 | E6: =Assumptions!E$25 | F6: =Assumptions!F$25
A7: EBITDA | B7: =B4*B6 | C7: =C4*C6 | D7: =D4*D6 | E7: =E4*E6 | F7: =F4*F6
A8: Less: Depreciation & amortization | B8: =B4*Assumptions!$B$28 | C8: =C4*Assumptions!$B$28 | D8: =D4*Assumptions!$B$28 | E8: =E4*Assumptions!$B$28 | F8: =F4*Assumptions!$B$28
A9: EBIT | B9: =B7-B8 | C9: =C7-C8 | D9: =D7-D8 | E9: =E7-E8 | F9: =F7-F8
A10: Tax rate | B10: =Assumptions!$B$9 | C10: =Assumptions!$B$9 | D10: =Assumptions!$B$9 | E10: =Assumptions!$B$9 | F10: =Assumptions!$B$9
A11: Less: Income tax | B11: =B9*B10 | C11: =C9*C10 | D11: =D9*D10 | E11: =E9*E10 | F11: =F9*F10
A12: NOPAT | B12: =B9-B11 | C12: =C9-C11 | D12: =D9-D11 | E12: =E9-E11 | F12: =F9-F11
A13: Add: Stock-based compensation | B13: =B4*Assumptions!B$29 | C13: =C4*Assumptions!C$29 | D13: =D4*Assumptions!D$29 | E13: =E4*Assumptions!E$29 | F13: =F4*Assumptions!F$29
A14: Less: Capital expenditures | B14: =B4*Assumptions!$B$30 | C14: =C4*Assumptions!$B$30 | D14: =D4*Assumptions!$B$30 | E14: =E4*Assumptions!$B$30 | F14: =F4*Assumptions!$B$30
A15: Less: Change in net working capital | B15: =(B4-Historicals!$E$4)*Assumptions!$B$31 | C15: =(C4-B4)*Assumptions!$B$31 | D15: =(D4-C4)*Assumptions!$B$31 | E15: =(E4-D4)*Assumptions!$B$31 | F15: =(F4-E4)*Assumptions!$B$31
A16: Unlevered free cash flow | B16: =B12+B8+B13-B14-B15 | C16: =C12+C8+C13-C14-C15 | D16: =D12+D8+D13-D14-D15 | E16: =E12+E8+E13-E14-E15 | F16: =F12+F8+F13-F14-F15
A17: Discount factor | B17: =1/(1+Assumptions!$B$16)^1 | C17: =1/(1+Assumptions!$B$16)^2 | D17: =1/(1+Assumptions!$B$16)^3 | E17: =1/(1+Assumptions!$B$16)^4 | F17: =1/(1+Assumptions!$B$16)^5
A18: Present value of FCF | B18: =B16*B17 | C18: =C16*C17 | D18: =D16*D17 | E18: =E16*E17 | F18: =F16*F17
A19: Sum of PV of FCF | B19: =SUM(B18:F18)
A20: Terminal value | B20: =F16*(1+Assumptions!$B$33)/(Assumptions!$B$16-Assumptions!$B$33)
A21: PV of terminal value | B21: =B20/(1+Assumptions!$B$16)^5
A22: Enterprise value | B22: =B19+B21
A23: Less: Net debt | B23: =Assumptions!$B$35
A24: Equity value | B24: =B22-B23
A25: Diluted shares outstanding (M) | B25: =Assumptions!$B$36
A26: Implied value per share ($) | B26: =B24/B25

Sheet DCF_Bear
A1: Robinhood Markets, Inc. (HOOD) — Discounted cash flow — bear case
A2: $ millions, except per-share. All formulas reference Assumptions / Historicals.
B3: 2026 | C3: 2027 | D3: 2028 | E3: 2029 | F3: 2030
A4: Revenue | B4: =Historicals!$E$4*(1+Assumptions!B$23) | C4: =B4*(1+Assumptions!C$23) | D4: =C4*(1+Assumptions!D$23) | E4: =D4*(1+Assumptions!E$23) | F4: =E4*(1+Assumptions!F$23)
A5: Revenue growth | B5: =B4/Historicals!$E$4-1 | C5: =C4/B4-1 | D5: =D4/C4-1 | E5: =E4/D4-1 | F5: =F4/E4-1
A6: EBITDA margin | B6: =Assumptions!B$26 | C6: =Assumptions!C$26 | D6: =Assumptions!D$26 | E6: =Assumptions!E$26 | F6: =Assumptions!F$26
A7: EBITDA | B7: =B4*B6 | C7: =C4*C6 | D7: =D4*D6 | E7: =E4*E6 | F7: =F4*F6
A8: Less: Depreciation & amortization | B8: =B4*Assumptions!$B$28 | C8: =C4*Assumptions!$B$28 | D8: =D4*Assumptions!$B$28 | E8: =E4*Assumptions!$B$28 | F8: =F4*Assumptions!$B$28
A9: EBIT | B9: =B7-B8 | C9: =C7-C8 | D9: =D7-D8 | E9: =E7-E8 | F9: =F7-F8
A10: Tax rate | B10: =Assumptions!$B$9 | C10: =Assumptions!$B$9 | D10: =Assumptions!$B$9 | E10: =Assumptions!$B$9 | F10: =Assumptions!$B$9
A11: Less: Income tax | B11: =B9*B10 | C11: =C9*C10 | D11: =D9*D10 | E11: =E9*E10 | F11: =F9*F10
A12: NOPAT | B12: =B9-B11 | C12: =C9-C11 | D12: =D9-D11 | E12: =E9-E11 | F12: =F9-F11
A13: Add: Stock-based compensation | B13: =B4*Assumptions!B$29 | C13: =C4*Assumptions!C$29 | D13: =D4*Assumptions!D$29 | E13: =E4*Assumptions!E$29 | F13: =F4*Assumptions!F$29
A14: Less: Capital expenditures | B14: =B4*Assumptions!$B$30 | C14: =C4*Assumptions!$B$30 | D14: =D4*Assumptions!$B$30 | E14: =E4*Assumptions!$B$30 | F14: =F4*Assumptions!$B$30
A15: Less: Change in net working capital | B15: =(B4-Historicals!$E$4)*Assumptions!$B$31 | C15: =(C4-B4)*Assumptions!$B$31 | D15: =(D4-C4)*Assumptions!$B$31 | E15: =(E4-D4)*Assumptions!$B$31 | F15: =(F4-E4)*Assumptions!$B$31
A16: Unlevered free cash flow | B16: =B12+B8+B13-B14-B15 | C16: =C12+C8+C13-C14-C15 | D16: =D12+D8+D13-D14-D15 | E16: =E12+E8+E13-E14-E15 | F16: =F12+F8+F13-F14-F15
A17: Discount factor | B17: =1/(1+Assumptions!$B$17)^1 | C17: =1/(1+Assumptions!$B$17)^2 | D17: =1/(1+Assumptions!$B$17)^3 | E17: =1/(1+Assumptions!$B$17)^4 | F17: =1/(1+Assumptions!$B$17)^5
A18: Present value of FCF | B18: =B16*B17 | C18: =C16*C17 | D18: =D16*D17 | E18: =E16*E17 | F18: =F16*F17
A19: Sum of PV of FCF | B19: =SUM(B18:F18)
A20: Terminal value | B20: =F16*(1+Assumptions!$B$34)/(Assumptions!$B$17-Assumptions!$B$34)
A21: PV of terminal value | B21: =B20/(1+Assumptions!$B$17)^5
A22: Enterprise value | B22: =B19+B21
A23: Less: Net debt | B23: =Assumptions!$B$35
A24: Equity value | B24: =B22-B23
A25: Diluted shares outstanding (M) | B25: =Assumptions!$B$36
A26: Implied value per share ($) | B26: =B24/B25

Sheet Comps
A1: Comparable companies — fintech / brokerage
A2: Market data as of 2026-10-19 (Yahoo Finance). $ millions, except price and per-share.
B3: HOOD | C3: COIN | D3: SOFI | E3: SCHW | F3: IBKR
A4: Price ($) | B4: 98.87 | C4: 173.16 | D4: 14.55 | E4: 91.96 | F4: 82.69
A5: Market cap ($M) | B5: 88892.3 | C5: 45686 | D5: 18792.3 | E5: 159029.7 | F5: 140888.5
A6: Enterprise value ($M) | B6: 87973.3 | C6: 43565.4 | D6: 18841.2 | E6: 130406.9 | F6: -40329.1
A7: Revenue, TTM ($M) | B7: 4932 | C7: 6043.8 | D7: 4268.4 | E7: 27061 | F7: 7058
A8: EBITDA, TTM ($M) | B8: 2180 | C8: 699.5 | D8: n/a | E8: n/a | F8: n/a
A9: Forward EPS ($) | B9: 3.43 | C9: 2.99 | D9: 0.82 | E9: 7.85 | F9: 3.31
A10: EV / Revenue | B10: =B6/B7 | C10: =C6/C7 | D10: =D6/D7 | E10: =E6/E7 | F10: =F6/F7
A11: EV / EBITDA | B11: =B6/B8 | C11: =C6/C8 | D11: n/a | E11: n/a | F11: n/a
A12: Trailing P/E | B12: 43.56 | C12: n/a | D12: 29.69 | E12: 15.72 | F12: 31.56
A13: Forward P/E | B13: =B4/B9 | C13: =C4/C9 | D13: =D4/D9 | E13: =E4/E9 | F13: =F4/F9
A15: HOOD implied valuation from peer multiples
A16: Median peer EV / Revenue (excl. IBKR: negative EV) | B16: =MEDIAN(C10:E10)
A17: Implied EV ($M) | B17: =B16*B7
A18: Less: Net debt ($M) | B18: =Assumptions!$B$35
A19: Implied equity ($M) | B19: =B17-B18
A20: Implied per share — EV/Revenue ($) | B20: =B19/Assumptions!$B$36 | C20: Not meaningful: HOOD's rate-driven revenue mix breaks EV/Revenue comparability; P/E is the operative broker multiple.
A22: Median peer forward P/E | B22: =MEDIAN(C13:F13)
A23: HOOD forward EPS ($) | B23: =B9
A24: Implied per share — forward P/E ($) | B24: =B22*B23

Sheet Sensitivity
A1: Sensitivity — base-case per-share value ($)
A2: Two-way sensitivity to WACC (±150 bps) and terminal growth (±100 bps). Live formulas off DCF_Base.
A3: WACC \ g | B3: =Assumptions!$B$32-0.010 | C3: =Assumptions!$B$32-0.005 | D3: =Assumptions!$B$32 | E3: =Assumptions!$B$32+0.005 | F3: =Assumptions!$B$32+0.010
A4: =Assumptions!$B$15-0.015 | B4: =(((DCF_Base!B16/(1+$A4)^1+DCF_Base!C16/(1+$A4)^2+DCF_Base!D16/(1+$A4)^3+DCF_Base!E16/(1+$A4)^4+DCF_Base!F16/(1+$A4)^5)+((DCF_Base!$F$16*(1+B$3)/($A4-B$3))/(1+$A4)^5)-Assumptions!$B$35)/Assumptions!$B$36 | C4: =(((DCF_Base!B16/(1+$A4)^1+DCF_Base!C16/(1+$A4)^2+DCF_Base!D16/(1+$A4)^3+DCF_Base!E16/(1+$A4)^4+DCF_Base!F16/(1+$A4)^5)+((DCF_Base!$F$16*(1+C$3)/($A4-C$3))/(1+$A4)^5)-Assumptions!$B$35)/Assumptions!$B$36 | D4: =(((DCF_Base!B16/(1+$A4)^1+DCF_Base!C16/(1+$A4)^2+DCF_Base!D16/(1+$A4)^3+DCF_Base!E16/(1+$A4)^4+DCF_Base!F16/(1+$A4)^5)+((DCF_Base!$F$16*(1+D$3)/($A4-D$3))/(1+$A4)^5)-Assumptions!$B$35)/Assumptions!$B$36 | E4: =(((DCF_Base!B16/(1+$A4)^1+DCF_Base!C16/(1+$A4)^2+DCF_Base!D16/(1+$A4)^3+DCF_Base!E16/(1+$A4)^4+DCF_Base!F16/(1+$A4)^5)+((DCF_Base!$F$16*(1+E$3)/($A4-E$3))/(1+$A4)^5)-Assumptions!$B$35)/Assumptions!$B$36 | F4: =(((DCF_Base!B16/(1+$A4)^1+DCF_Base!C16/(1+$A4)^2+DCF_Base!D16/(1+$A4)^3+DCF_Base!E16/(1+$A4)^4+DCF_Base!F16/(1+$A4)^5)+((DCF_Base!$F$16*(1+F$3)/($A4-F$3))/(1+$A4)^5)-Assumptions!$B$35)/Assumptions!$B$36
A5: =Assumptions!$B$15-0.010 | B5: =(((DCF_Base!B16/(1+$A5)^1+DCF_Base!C16/(1+$A5)^2+DCF_Base!D16/(1+$A5)^3+DCF_Base!E16/(1+$A5)^4+DCF_Base!F16/(1+$A5)^5)+((DCF_Base!$F$16*(1+B$3)/($A5-B$3))/(1+$A5)^5)-Assumptions!$B$35)/Assumptions!$B$36 | C5: =(((DCF_Base!B16/(1+$A5)^1+DCF_Base!C16/(1+$A5)^2+DCF_Base!D16/(1+$A5)^3+DCF_Base!E16/(1+$A5)^4+DCF_Base!F16/(1+$A5)^5)+((DCF_Base!$F$16*(1+C$3)/($A5-C$3))/(1+$A5)^5)-Assumptions!$B$35)/Assumptions!$B$36 | D5: =(((DCF_Base!B16/(1+$A5)^1+DCF_Base!C16/(1+$A5)^2+DCF_Base!D16/(1+$A5)^3+DCF_Base!E16/(1+$A5)^4+DCF_Base!F16/(1+$A5)^5)+((DCF_Base!$F$16*(1+D$3)/($A5-D$3))/(1+$A5)^5)-Assumptions!$B$35)/Assumptions!$B$36 | E5: =(((DCF_Base!B16/(1+$A5)^1+DCF_Base!C16/(1+$A5)^2+DCF_Base!D16/(1+$A5)^3+DCF_Base!E16/(1+$A5)^4+DCF_Base!F16/(1+$A5)^5)+((DCF_Base!$F$16*(1+E$3)/($A5-E$3))/(1+$A5)^5)-Assumptions!$B$35)/Assumptions!$B$36 | F5: =(((DCF_Base!B16/(1+$A5)^1+DCF_Base!C16/(1+$A5)^2+DCF_Base!D16/(1+$A5)^3+DCF_Base!E16/(1+$A5)^4+DCF_Base!F16/(1+$A5)^5)+((DCF_Base!$F$16*(1+F$3)/($A5-F$3))/(1+$A5)^5)-Assumptions!$B$35)/Assumptions!$B$36
A6: =Assumptions!$B$15-0.005 | B6: =(((DCF_Base!B16/(1+$A6)^1+DCF_Base!C16/(1+$A6)^2+DCF_Base!D16/(1+$A6)^3+DCF_Base!E16/(1+$A6)^4+DCF_Base!F16/(1+$A6)^5)+((DCF_Base!$F$16*(1+B$3)/($A6-B$3))/(1+$A6)^5)-Assumptions!$B$35)/Assumptions!$B$36 | C6: =(((DCF_Base!B16/(1+$A6)^1+DCF_Base!C16/(1+$A6)^2+DCF_Base!D16/(1+$A6)^3+DCF_Base!E16/(1+$A6)^4+DCF_Base!F16/(1+$A6)^5)+((DCF_Base!$F$16*(1+C$3)/($A6-C$3))/(1+$A6)^5)-Assumptions!$B$35)/Assumptions!$B$36 | D6: =(((DCF_Base!B16/(1+$A6)^1+DCF_Base!C16/(1+$A6)^2+DCF_Base!D16/(1+$A6)^3+DCF_Base!E16/(1+$A6)^4+DCF_Base!F16/(1+$A6)^5)+((DCF_Base!$F$16*(1+D$3)/($A6-D$3))/(1+$A6)^5)-Assumptions!$B$35)/Assumptions!$B$36 | E6: =(((DCF_Base!B16/(1+$A6)^1+DCF_Base!C16/(1+$A6)^2+DCF_Base!D16/(1+$A6)^3+DCF_Base!E16/(1+$A6)^4+DCF_Base!F16/(1+$A6)^5)+((DCF_Base!$F$16*(1+E$3)/($A6-E$3))/(1+$A6)^5)-Assumptions!$B$35)/Assumptions!$B$36 | F6: =(((DCF_Base!B16/(1+$A6)^1+DCF_Base!C16/(1+$A6)^2+DCF_Base!D16/(1+$A6)^3+DCF_Base!E16/(1+$A6)^4+DCF_Base!F16/(1+$A6)^5)+((DCF_Base!$F$16*(1+F$3)/($A6-F$3))/(1+$A6)^5)-Assumptions!$B$35)/Assumptions!$B$36
A7: =Assumptions!$B$15 | B7: =(((DCF_Base!B16/(1+$A7)^1+DCF_Base!C16/(1+$A7)^2+DCF_Base!D16/(1+$A7)^3+DCF_Base!E16/(1+$A7)^4+DCF_Base!F16/(1+$A7)^5)+((DCF_Base!$F$16*(1+B$3)/($A7-B$3))/(1+$A7)^5)-Assumptions!$B$35)/Assumptions!$B$36 | C7: =(((DCF_Base!B16/(1+$A7)^1+DCF_Base!C16/(1+$A7)^2+DCF_Base!D16/(1+$A7)^3+DCF_Base!E16/(1+$A7)^4+DCF_Base!F16/(1+$A7)^5)+((DCF_Base!$F$16*(1+C$3)/($A7-C$3))/(1+$A7)^5)-Assumptions!$B$35)/Assumptions!$B$36 | D7: =(((DCF_Base!B16/(1+$A7)^1+DCF_Base!C16/(1+$A7)^2+DCF_Base!D16/(1+$A7)^3+DCF_Base!E16/(1+$A7)^4+DCF_Base!F16/(1+$A7)^5)+((DCF_Base!$F$16*(1+D$3)/($A7-D$3))/(1+$A7)^5)-Assumptions!$B$35)/Assumptions!$B$36 | E7: =(((DCF_Base!B16/(1+$A7)^1+DCF_Base!C16/(1+$A7)^2+DCF_Base!D16/(1+$A7)^3+DCF_Base!E16/(1+$A7)^4+DCF_Base!F16/(1+$A7)^5)+((DCF_Base!$F$16*(1+E$3)/($A7-E$3))/(1+$A7)^5)-Assumptions!$B$35)/Assumptions!$B$36 | F7: =(((DCF_Base!B16/(1+$A7)^1+DCF_Base!C16/(1+$A7)^2+DCF_Base!D16/(1+$A7)^3+DCF_Base!E16/(1+$A7)^4+DCF_Base!F16/(1+$A7)^5)+((DCF_Base!$F$16*(1+F$3)/($A7-F$3))/(1+$A7)^5)-Assumptions!$B$35)/Assumptions!$B$36
A8: =Assumptions!$B$15+0.005 | B8: =(((DCF_Base!B16/(1+$A8)^1+DCF_Base!C16/(1+$A8)^2+DCF_Base!D16/(1+$A8)^3+DCF_Base!E16/(1+$A8)^4+DCF_Base!F16/(1+$A8)^5)+((DCF_Base!$F$16*(1+B$3)/($A8-B$3))/(1+$A8)^5)-Assumptions!$B$35)/Assumptions!$B$36 | C8: =(((DCF_Base!B16/(1+$A8)^1+DCF_Base!C16/(1+$A8)^2+DCF_Base!D16/(1+$A8)^3+DCF_Base!E16/(1+$A8)^4+DCF_Base!F16/(1+$A8)^5)+((DCF_Base!$F$16*(1+C$3)/($A8-C$3))/(1+$A8)^5)-Assumptions!$B$35)/Assumptions!$B$36 | D8: =(((DCF_Base!B16/(1+$A8)^1+DCF_Base!C16/(1+$A8)^2+DCF_Base!D16/(1+$A8)^3+DCF_Base!E16/(1+$A8)^4+DCF_Base!F16/(1+$A8)^5)+((DCF_Base!$F$16*(1+D$3)/($A8-D$3))/(1+$A8)^5)-Assumptions!$B$35)/Assumptions!$B$36 | E8: =(((DCF_Base!B16/(1+$A8)^1+DCF_Base!C16/(1+$A8)^2+DCF_Base!D16/(1+$A8)^3+DCF_Base!E16/(1+$A8)^4+DCF_Base!F16/(1+$A8)^5)+((DCF_Base!$F$16*(1+E$3)/($A8-E$3))/(1+$A8)^5)-Assumptions!$B$35)/Assumptions!$B$36 | F8: =(((DCF_Base!B16/(1+$A8)^1+DCF_Base!C16/(1+$A8)^2+DCF_Base!D16/(1+$A8)^3+DCF_Base!E16/(1+$A8)^4+DCF_Base!F16/(1+$A8)^5)+((DCF_Base!$F$16*(1+F$3)/($A8-F$3))/(1+$A8)^5)-Assumptions!$B$35)/Assumptions!$B$36
A9: =Assumptions!$B$15+0.010 | B9: =(((DCF_Base!B16/(1+$A9)^1+DCF_Base!C16/(1+$A9)^2+DCF_Base!D16/(1+$A9)^3+DCF_Base!E16/(1+$A9)^4+DCF_Base!F16/(1+$A9)^5)+((DCF_Base!$F$16*(1+B$3)/($A9-B$3))/(1+$A9)^5)-Assumptions!$B$35)/Assumptions!$B$36 | C9: =(((DCF_Base!B16/(1+$A9)^1+DCF_Base!C16/(1+$A9)^2+DCF_Base!D16/(1+$A9)^3+DCF_Base!E16/(1+$A9)^4+DCF_Base!F16/(1+$A9)^5)+((DCF_Base!$F$16*(1+C$3)/($A9-C$3))/(1+$A9)^5)-Assumptions!$B$35)/Assumptions!$B$36 | D9: =(((DCF_Base!B16/(1+$A9)^1+DCF_Base!C16/(1+$A9)^2+DCF_Base!D16/(1+$A9)^3+DCF_Base!E16/(1+$A9)^4+DCF_Base!F16/(1+$A9)^5)+((DCF_Base!$F$16*(1+D$3)/($A9-D$3))/(1+$A9)^5)-Assumptions!$B$35)/Assumptions!$B$36 | E9: =(((DCF_Base!B16/(1+$A9)^1+DCF_Base!C16/(1+$A9)^2+DCF_Base!D16/(1+$A9)^3+DCF_Base!E16/(1+$A9)^4+DCF_Base!F16/(1+$A9)^5)+((DCF_Base!$F$16*(1+E$3)/($A9-E$3))/(1+$A9)^5)-Assumptions!$B$35)/Assumptions!$B$36 | F9: =(((DCF_Base!B16/(1+$A9)^1+DCF_Base!C16/(1+$A9)^2+DCF_Base!D16/(1+$A9)^3+DCF_Base!E16/(1+$A9)^4+DCF_Base!F16/(1+$A9)^5)+((DCF_Base!$F$16*(1+F$3)/($A9-F$3))/(1+$A9)^5)-Assumptions!$B$35)/Assumptions!$B$36
A10: =Assumptions!$B$15+0.015 | B10: =(((DCF_Base!B16/(1+$A10)^1+DCF_Base!C16/(1+$A10)^2+DCF_Base!D16/(1+$A10)^3+DCF_Base!E16/(1+$A10)^4+DCF_Base!F16/(1+$A10)^5)+((DCF_Base!$F$16*(1+B$3)/($A10-B$3))/(1+$A10)^5)-Assumptions!$B$35)/Assumptions!$B$36 | C10: =(((DCF_Base!B16/(1+$A10)^1+DCF_Base!C16/(1+$A10)^2+DCF_Base!D16/(1+$A10)^3+DCF_Base!E16/(1+$A10)^4+DCF_Base!F16/(1+$A10)^5)+((DCF_Base!$F$16*(1+C$3)/($A10-C$3))/(1+$A10)^5)-Assumptions!$B$35)/Assumptions!$B$36 | D10: =(((DCF_Base!B16/(1+$A10)^1+DCF_Base!C16/(1+$A10)^2+DCF_Base!D16/(1+$A10)^3+DCF_Base!E16/(1+$A10)^4+DCF_Base!F16/(1+$A10)^5)+((DCF_Base!$F$16*(1+D$3)/($A10-D$3))/(1+$A10)^5)-Assumptions!$B$35)/Assumptions!$B$36 | E10: =(((DCF_Base!B16/(1+$A10)^1+DCF_Base!C16/(1+$A10)^2+DCF_Base!D16/(1+$A10)^3+DCF_Base!E16/(1+$A10)^4+DCF_Base!F16/(1+$A10)^5)+((DCF_Base!$F$16*(1+E$3)/($A10-E$3))/(1+$A10)^5)-Assumptions!$B$35)/Assumptions!$B$36 | F10: =(((DCF_Base!B16/(1+$A10)^1+DCF_Base!C16/(1+$A10)^2+DCF_Base!D16/(1+$A10)^3+DCF_Base!E16/(1+$A10)^4+DCF_Base!F16/(1+$A10)^5)+((DCF_Base!$F$16*(1+F$3)/($A10-F$3))/(1+$A10)^5)-Assumptions!$B$35)/Assumptions!$B$36

Sheet Checks
A1: Verification appendix
A2: Tie-outs and data provenance. Every [DATA] input is sourced; every [JUDGMENT] input carries a rationale on Assumptions.
A3: Check | B3: Detail | C3: Status
A4: Net income ties across statements | B4: Income-statement net income = cash-flow-statement starting net income for FY2022–2025 (max diff $0.0M) | C4: PASS
A5: Revenue sourced from filings | B5: FY2022–2025 total revenue 1,358.0 / 1,865.0 / 2,951.0 / 4,473.0 ($M) from Yahoo Finance annual income statement; FY2021 column blank in source — excluded | C5: PASS
A6: Share count | B6: 899.1M outstanding (Yahoo Finance / stockanalysis.com, Oct 2026); FY2025 diluted weighted avg 918.8M (10-K via Yahoo). Used 899.1M; delta <3% | C6: PASS
A7: Net debt bridge | B7: Q2 2026 balance sheet: total debt $22,706.0M less cash & equivalents $5,362.0M = net debt $17,344.0M | C7: PASS
A8: Beta | B8: 2.35 (Yahoo Finance, 2026-10-19); cross-checked 2.35 (MarketBeat, stockanalysis.com), 2.48 (Finnhub) | C8: PASS
A9: Risk-free rate | B9: US 10Y 5.085% on 2026-10-19 (Reuters); Gate Ventures recap 5.09%; CoinDesk/CoinEdition ~5.10%. Used 5.1% | C9: PASS
A10: Comps market data as-of | B10: COIN / SOFI / SCHW / IBKR prices and financials pulled 2026-10-19 via Yahoo Finance (Oct 16 closes) | C10: PASS
A11: FCF bridge reconciles | B11: Formula check: EV = sum of PV of FCF + PV of terminal value | C11: =IF(ABS(DCF_Base!B22-(DCF_Base!B19+DCF_Base!B21))<0.5,"PASS","FAIL")
A12: Per-share arithmetic | B12: Formula check: per-share = equity value / shares | C12: =IF(ABS(DCF_Base!B26-DCF_Base!B24/DCF_Base!B25)<0.01,"PASS","FAIL")
A13: Sensitivity centers on base case | B13: Formula check: center cell of Sensitivity = DCF_Base per-share | C13: =IF(ABS(D7-DCF_Base!B26)<0.05,"PASS","FAIL")
A14: DCF vs market gap is explainable | B14: Base per-share trails $98.87 because a 13.4% WACC (beta 2.35 × 5.1% risk-free) discounts high-teens growth hard; the market price implies ~40% 5-yr CAGR or a ~10% WACC (aggressive rate-cut pricing) | C14: PASS
A15: Tax normalization | B15: 2024 tax provision was –$347M (benefit); model uses 21% statutory forward rate — flagged as judgment on Assumptions | C15: PASS
A16: IBKR excluded from EV comps | B16: Negative enterprise value (–$40.3B) breaks the multiple; median EV/Revenue uses COIN/SOFI/SCHW only | C16: PASS

Sheet Sources
A1: Sources
A2: Full URLs and access dates for every external input.
A3: # | B3: Source | C3: URL | D3: Accessed | E3: Used for
A4: 1 | B4: Yahoo Finance — HOOD quote & financials | C4: https://finance.yahoo.com/quote/HOOD | D4: 2026-10-19 | E4: Price, beta, shares, annual/quarterly statements
A5: 2 | B5: Yahoo Finance — COIN | C5: https://finance.yahoo.com/quote/COIN | D5: 2026-10-19 | E5: Comps market data
A6: 3 | B6: Yahoo Finance — SOFI | C6: https://finance.yahoo.com/quote/SOFI | D6: 2026-10-19 | E6: Comps market data
A7: 4 | B7: Yahoo Finance — SCHW | C7: https://finance.yahoo.com/quote/SCHW | D7: 2026-10-19 | E7: Comps market data
A8: 5 | B8: Yahoo Finance — IBKR | C8: https://finance.yahoo.com/quote/IBKR | D8: 2026-10-19 | E8: Comps market data
A9: 6 | B9: Reuters — 10Y yield 5.085% on Oct 19, 2026 | C9: https://www.reuters.com/business/wall-st-futures-climb-ai-stocks-rebound-oil-yields-fall-2026-10-19/ | D9: 2026-10-19 | E9: Risk-free rate
A10: 7 | B10: stockanalysis.com — HOOD overview | C10: https://StockAnalysis.com/stocks/hood/ | D10: 2026-10-19 | E10: Shares outstanding cross-check (899.08M)
A11: 8 | B11: MarketBeat — HOOD | C11: https://www.marketbeat.com/stocks/NASDAQ/HOOD/ | D11: 2026-10-19 | E11: Beta (2.35) and shares cross-check
A12: 9 | B12: Finnhub — HOOD | C12: https://finnhub.io/?q=%22HOOD%22 | D12: 2026-10-19 | E12: Beta cross-check (2.48)
A13: 10 | B13: TipRanks — HOOD statistics | C13: https://www.tipranks.com/stocks/hood/statistics | D13: 2026-10-19 | E13: Cash/debt cross-check; street growth-forecast context
